[{"timestamp": "2025-02-27T00:00:00Z", "open": 376.75, "high": 376.75, "low": 368.5, "close": 370.75, "volume": 36396}, {"timestamp": "2025-02-28T00:00:00Z", "open": 370.75, "high": 377.5, "low": 369.5, "close": 373.5, "volume": 43024}, {"timestamp": "2025-03-03T00:00:00Z", "open": 372.75, "high": 376.5, "low": 372.5, "close": 372.5, "volume": 34992}, {"timestamp": "2025-03-04T00:00:00Z", "open": 372.5, "high": 376.0, "low": 359.0, "close": 362.0, "volume": 42220}, {"timestamp": "2025-03-05T00:00:00Z", "open": 364.75, "high": 369.5, "low": 356.25, "close": 364.5, "volume": 35606}, {"timestamp": "2025-03-06T00:00:00Z", "open": 372.0, "high": 400.75, "low": 369.25, "close": 400.75, "volume": 151027}, {"timestamp": "2025-03-07T00:00:00Z", "open": 420.0, "high": 440.75, "low": 409.75, "close": 440.75, "volume": 184777}, {"timestamp": "2025-03-10T00:00:00Z", "open": 454.25, "high": 484.75, "low": 419.25, "close": 428.75, "volume": 435952}, {"timestamp": "2025-03-11T00:00:00Z", "open": 443.75, "high": 460.0, "low": 428.5, "close": 432.25, "volume": 238809}, {"timestamp": "2025-03-12T00:00:00Z", "open": 428.5, "high": 459.0, "low": 422.0, "close": 433.0, "volume": 248221}, {"timestamp": "2025-03-13T00:00:00Z", "open": 433.0, "high": 438.0, "low": 427.25, "close": 431.0, "volume": 71202}, {"timestamp": "2025-03-14T00:00:00Z", "open": 431.0, "high": 433.75, "low": 424.75, "close": 427.25, "volume": 48289}, {"timestamp": "2025-03-17T00:00:00Z", "open": 431.0, "high": 440.0, "low": 427.5, "close": 436.5, "volume": 73715}, {"timestamp": "2025-03-18T00:00:00Z", "open": 436.75, "high": 455.0, "low": 435.0, "close": 441.25, "volume": 121216}, {"timestamp": "2025-03-19T00:00:00Z", "open": 425.0, "high": 425.0, "low": 397.25, "close": 397.5, "volume": 83118}, {"timestamp": "2025-03-20T00:00:00Z", "open": 391.25, "high": 417.75, "low": 391.25, "close": 406.0, "volume": 53869}, {"timestamp": "2025-03-21T00:00:00Z", "open": 406.0, "high": 406.0, "low": 371.0, "close": 389.0, "volume": 57551}, {"timestamp": "2025-03-24T00:00:00Z", "open": 385.25, "high": 403.0, "low": 370.25, "close": 394.5, "volume": 78103}, {"timestamp": "2025-03-25T00:00:00Z", "open": 396.0, "high": 406.25, "low": 394.5, "close": 403.75, "volume": 56246}, {"timestamp": "2025-03-26T00:00:00Z", "open": 407.5, "high": 407.5, "low": 394.75, "close": 398.75, "volume": 42158}, {"timestamp": "2025-03-27T00:00:00Z", "open": 402.0, "high": 410.0, "low": 394.25, "close": 394.75, "volume": 62676}, {"timestamp": "2025-03-28T00:00:00Z", "open": 394.75, "high": 398.75, "low": 383.25, "close": 397.25, "volume": 46845}, {"timestamp": "2025-04-02T00:00:00Z", "open": 397.5, "high": 423.0, "low": 394.5, "close": 411.0, "volume": 77420}, {"timestamp": "2025-04-03T00:00:00Z", "open": 410.75, "high": 418.75, "low": 405.0, "close": 411.5, "volume": 50741}, {"timestamp": "2025-04-04T00:00:00Z", "open": 411.5, "high": 417.5, "low": 405.0, "close": 406.75, "volume": 45130}, {"timestamp": "2025-04-07T00:00:00Z", "open": 395.0, "high": 400.0, "low": 386.0, "close": 395.25, "volume": 50768}, {"timestamp": "2025-04-08T00:00:00Z", "open": 396.0, "high": 417.5, "low": 396.0, "close": 403.75, "volume": 36064}, {"timestamp": "2025-04-09T00:00:00Z", "open": 404.0, "high": 404.25, "low": 385.0, "close": 393.0, "volume": 42419}, {"timestamp": "2025-04-10T00:00:00Z", "open": 401.75, "high": 414.75, "low": 396.0, "close": 399.25, "volume": 58956}, {"timestamp": "2025-04-11T00:00:00Z", "open": 397.0, "high": 410.0, "low": 394.25, "close": 401.5, "volume": 28822}, {"timestamp": "2025-04-14T00:00:00Z", "open": 401.75, "high": 408.75, "low": 400.0, "close": 402.0, "volume": 31995}, {"timestamp": "2025-04-15T00:00:00Z", "open": 406.5, "high": 424.75, "low": 402.0, "close": 411.0, "volume": 118442}, {"timestamp": "2025-04-16T00:00:00Z", "open": 409.75, "high": 411.0, "low": 398.75, "close": 399.75, "volume": 48823}, {"timestamp": "2025-04-17T00:00:00Z", "open": 399.75, "high": 405.75, "low": 392.0, "close": 398.75, "volume": 34924}, {"timestamp": "2025-04-18T00:00:00Z", "open": 398.75, "high": 402.75, "low": 393.25, "close": 397.0, "volume": 31605}, {"timestamp": "2025-04-21T00:00:00Z", "open": 394.0, "high": 402.25, "low": 393.0, "close": 396.75, "volume": 32939}, {"timestamp": "2025-04-22T00:00:00Z", "open": 397.25, "high": 401.75, "low": 387.0, "close": 387.0, "volume": 29408}, {"timestamp": "2025-04-24T00:00:00Z", "open": 387.0, "high": 395.0, "low": 385.0, "close": 388.0, "volume": 33485}, {"timestamp": "2025-04-25T00:00:00Z", "open": 393.5, "high": 393.5, "low": 386.75, "close": 388.5, "volume": 25171}, {"timestamp": "2025-04-28T00:00:00Z", "open": 391.25, "high": 398.0, "low": 391.25, "close": 392.5, "volume": 68532}, {"timestamp": "2025-04-29T00:00:00Z", "open": 390.5, "high": 399.0, "low": 386.25, "close": 397.5, "volume": 58042}, {"timestamp": "2025-04-30T00:00:00Z", "open": 397.0, "high": 437.25, "low": 384.0, "close": 424.25, "volume": 62178}, {"timestamp": "2025-05-02T00:00:00Z", "open": 416.0, "high": 416.25, "low": 397.75, "close": 397.75, "volume": 92084}, {"timestamp": "2025-05-05T00:00:00Z", "open": 397.75, "high": 399.5, "low": 387.25, "close": 391.0, "volume": 36038}, {"timestamp": "2025-05-06T00:00:00Z", "open": 391.0, "high": 395.25, "low": 390.5, "close": 391.0, "volume": 32811}, {"timestamp": "2025-05-07T00:00:00Z", "open": 390.5, "high": 396.75, "low": 386.75, "close": 388.75, "volume": 39302}, {"timestamp": "2025-05-08T00:00:00Z", "open": 388.75, "high": 398.5, "low": 385.0, "close": 392.5, "volume": 53675}, {"timestamp": "2025-05-09T00:00:00Z", "open": 392.5, "high": 395.25, "low": 390.25, "close": 392.5, "volume": 24189}, {"timestamp": "2025-05-12T00:00:00Z", "open": 390.75, "high": 395.0, "low": 387.0, "close": 389.75, "volume": 66273}, {"timestamp": "2025-05-13T00:00:00Z", "open": 389.75, "high": 389.75, "low": 384.0, "close": 387.75, "volume": 27549}, {"timestamp": "2025-05-14T00:00:00Z", "open": 389.75, "high": 397.0, "low": 382.0, "close": 384.0, "volume": 37757}, {"timestamp": "2025-05-15T00:00:00Z", "open": 384.5, "high": 390.0, "low": 375.0, "close": 378.0, "volume": 38637}, {"timestamp": "2025-05-16T00:00:00Z", "open": 379.0, "high": 383.5, "low": 377.75, "close": 382.0, "volume": 21802}, {"timestamp": "2025-05-20T00:00:00Z", "open": 385.0, "high": 389.75, "low": 374.75, "close": 376.25, "volume": 28245}, {"timestamp": "2025-05-21T00:00:00Z", "open": 379.5, "high": 379.5, "low": 371.5, "close": 372.0, "volume": 19171}, {"timestamp": "2025-05-22T00:00:00Z", "open": 371.5, "high": 376.25, "low": 370.5, "close": 371.25, "volume": 29558}, {"timestamp": "2025-05-23T00:00:00Z", "open": 372.25, "high": 373.0, "low": 366.5, "close": 366.75, "volume": 23928}, {"timestamp": "2025-05-26T00:00:00Z", "open": 366.75, "high": 369.0, "low": 365.25, "close": 365.25, "volume": 16948}, {"timestamp": "2025-05-27T00:00:00Z", "open": 365.25, "high": 369.75, "low": 361.0, "close": 364.5, "volume": 27268}, {"timestamp": "2025-05-28T00:00:00Z", "open": 362.75, "high": 368.0, "low": 356.5, "close": 360.0, "volume": 28529}, {"timestamp": "2025-05-29T00:00:00Z", "open": 360.0, "high": 389.5, "low": 357.0, "close": 364.5, "volume": 130231}, {"timestamp": "2025-05-30T00:00:00Z", "open": 365.25, "high": 366.0, "low": 353.0, "close": 357.0, "volume": 39087}, {"timestamp": "2025-06-02T00:00:00Z", "open": 360.0, "high": 361.0, "low": 351.25, "close": 353.5, "volume": 26206}, {"timestamp": "2025-06-03T00:00:00Z", "open": 354.0, "high": 370.25, "low": 354.0, "close": 358.25, "volume": 21916}, {"timestamp": "2025-06-04T00:00:00Z", "open": 359.0, "high": 364.0, "low": 357.75, "close": 361.75, "volume": 33257}, {"timestamp": "2025-06-05T00:00:00Z", "open": 361.75, "high": 365.0, "low": 358.25, "close": 361.5, "volume": 8576}, {"timestamp": "2025-06-10T00:00:00Z", "open": 363.25, "high": 367.25, "low": 362.0, "close": 362.75, "volume": 41182}, {"timestamp": "2025-06-11T00:00:00Z", "open": 362.75, "high": 365.5, "low": 361.0, "close": 363.75, "volume": 32504}, {"timestamp": "2025-06-12T00:00:00Z", "open": 363.75, "high": 363.75, "low": 354.0, "close": 354.0, "volume": 22907}, {"timestamp": "2025-06-13T00:00:00Z", "open": 350.0, "high": 355.75, "low": 332.25, "close": 355.75, "volume": 54419}, {"timestamp": "2025-06-16T00:00:00Z", "open": 355.0, "high": 363.0, "low": 346.5, "close": 352.0, "volume": 43919}, {"timestamp": "2025-06-17T00:00:00Z", "open": 361.0, "high": 361.0, "low": 349.0, "close": 351.0, "volume": 19596}, {"timestamp": "2025-06-18T00:00:00Z", "open": 350.75, "high": 350.75, "low": 338.0, "close": 340.5, "volume": 25660}, {"timestamp": "2025-06-19T00:00:00Z", "open": 344.75, "high": 356.0, "low": 337.5, "close": 337.5, "volume": 41569}, {"timestamp": "2025-06-20T00:00:00Z", "open": 340.0, "high": 352.25, "low": 337.0, "close": 342.75, "volume": 53055}, {"timestamp": "2025-06-23T00:00:00Z", "open": 333.5, "high": 342.0, "low": 332.25, "close": 333.0, "volume": 33139}, {"timestamp": "2025-06-24T00:00:00Z", "open": 350.0, "high": 350.0, "low": 337.5, "close": 343.5, "volume": 35308}, {"timestamp": "2025-06-25T00:00:00Z", "open": 343.5, "high": 348.0, "low": 341.0, "close": 342.25, "volume": 26851}, {"timestamp": "2025-06-26T00:00:00Z", "open": 344.0, "high": 347.25, "low": 341.25, "close": 342.0, "volume": 29422}, {"timestamp": "2025-06-27T00:00:00Z", "open": 345.5, "high": 351.0, "low": 339.0, "close": 341.75, "volume": 26688}, {"timestamp": "2025-06-30T00:00:00Z", "open": 341.75, "high": 362.0, "low": 341.75, "close": 353.25, "volume": 103013}, {"timestamp": "2025-07-01T00:00:00Z", "open": 353.25, "high": 358.5, "low": 349.75, "close": 355.75, "volume": 46677}, {"timestamp": "2025-07-02T00:00:00Z", "open": 357.5, "high": 363.25, "low": 355.25, "close": 357.0, "volume": 63458}, {"timestamp": "2025-07-03T00:00:00Z", "open": 359.75, "high": 366.0, "low": 359.0, "close": 364.25, "volume": 49867}, {"timestamp": "2025-07-04T00:00:00Z", "open": 364.25, "high": 369.0, "low": 360.5, "close": 363.0, "volume": 27393}, {"timestamp": "2025-07-07T00:00:00Z", "open": 360.25, "high": 360.25, "low": 351.5, "close": 352.25, "volume": 30913}, {"timestamp": "2025-07-08T00:00:00Z", "open": 352.5, "high": 361.0, "low": 347.0, "close": 356.0, "volume": 47682}, {"timestamp": "2025-07-09T00:00:00Z", "open": 354.0, "high": 387.0, "low": 354.0, "close": 367.0, "volume": 190241}, {"timestamp": "2025-07-10T00:00:00Z", "open": 366.25, "high": 392.5, "low": 360.25, "close": 387.5, "volume": 137031}, {"timestamp": "2025-07-11T00:00:00Z", "open": 390.0, "high": 426.25, "low": 384.0, "close": 394.0, "volume": 582055}, {"timestamp": "2025-07-14T00:00:00Z", "open": 394.0, "high": 409.5, "low": 393.0, "close": 400.5, "volume": 148273}, {"timestamp": "2025-07-16T00:00:00Z", "open": 407.5, "high": 411.75, "low": 386.5, "close": 388.25, "volume": 110648}, {"timestamp": "2025-07-17T00:00:00Z", "open": 388.5, "high": 399.5, "low": 388.5, "close": 395.0, "volume": 69598}, {"timestamp": "2025-07-18T00:00:00Z", "open": 395.0, "high": 405.5, "low": 391.25, "close": 394.0, "volume": 76038}, {"timestamp": "2025-07-21T00:00:00Z", "open": 395.0, "high": 403.0, "low": 393.5, "close": 398.25, "volume": 65079}, {"timestamp": "2025-07-22T00:00:00Z", "open": 402.0, "high": 405.75, "low": 396.25, "close": 402.25, "volume": 51075}, {"timestamp": "2025-07-23T00:00:00Z", "open": 405.0, "high": 406.5, "low": 393.0, "close": 394.25, "volume": 47688}, {"timestamp": "2025-07-24T00:00:00Z", "open": 394.0, "high": 403.5, "low": 392.25, "close": 399.0, "volume": 60090}, {"timestamp": "2025-07-25T00:00:00Z", "open": 400.25, "high": 424.25, "low": 395.5, "close": 417.5, "volume": 187923}, {"timestamp": "2025-07-28T00:00:00Z", "open": 420.0, "high": 423.0, "low": 408.0, "close": 411.75, "volume": 98515}, {"timestamp": "2025-07-29T00:00:00Z", "open": 414.25, "high": 414.75, "low": 401.5, "close": 401.5, "volume": 49193}, {"timestamp": "2025-07-30T00:00:00Z", "open": 401.5, "high": 415.25, "low": 400.0, "close": 403.0, "volume": 78844}, {"timestamp": "2025-07-31T00:00:00Z", "open": 402.25, "high": 407.5, "low": 401.75, "close": 405.25, "volume": 43363}, {"timestamp": "2025-08-01T00:00:00Z", "open": 405.25, "high": 414.0, "low": 405.25, "close": 406.0, "volume": 48521}, {"timestamp": "2025-08-04T00:00:00Z", "open": 410.0, "high": 430.25, "low": 406.0, "close": 424.75, "volume": 102080}, {"timestamp": "2025-08-05T00:00:00Z", "open": 424.75, "high": 425.5, "low": 414.0, "close": 415.75, "volume": 67597}, {"timestamp": "2025-08-06T00:00:00Z", "open": 423.5, "high": 429.75, "low": 415.5, "close": 420.0, "volume": 92926}, {"timestamp": "2025-08-07T00:00:00Z", "open": 429.0, "high": 431.5, "low": 419.5, "close": 420.0, "volume": 64124}, {"timestamp": "2025-08-08T00:00:00Z", "open": 418.0, "high": 424.0, "low": 414.0, "close": 418.25, "volume": 40112}, {"timestamp": "2025-08-11T00:00:00Z", "open": 415.5, "high": 422.0, "low": 415.0, "close": 415.0, "volume": 29483}, {"timestamp": "2025-08-12T00:00:00Z", "open": 415.5, "high": 418.0, "low": 409.0, "close": 410.25, "volume": 33535}, {"timestamp": "2025-08-13T00:00:00Z", "open": 410.5, "high": 415.5, "low": 410.0, "close": 410.5, "volume": 33057}, {"timestamp": "2025-08-14T00:00:00Z", "open": 410.25, "high": 413.25, "low": 402.0, "close": 406.25, "volume": 36907}, {"timestamp": "2025-08-15T00:00:00Z", "open": 406.0, "high": 413.25, "low": 405.75, "close": 410.5, "volume": 33011}, {"timestamp": "2025-08-18T00:00:00Z", "open": 410.5, "high": 427.5, "low": 410.5, "close": 421.75, "volume": 72301}, {"timestamp": "2025-08-19T00:00:00Z", "open": 421.75, "high": 423.25, "low": 416.0, "close": 416.5, "volume": 29944}, {"timestamp": "2025-08-20T00:00:00Z", "open": 409.5, "high": 411.0, "low": 398.0, "close": 402.0, "volume": 78607}, {"timestamp": "2025-08-21T00:00:00Z", "open": 409.5, "high": 409.5, "low": 402.0, "close": 404.5, "volume": 48332}, {"timestamp": "2025-08-22T00:00:00Z", "open": 404.5, "high": 420.5, "low": 404.5, "close": 419.0, "volume": 168703}, {"timestamp": "2025-08-25T00:00:00Z", "open": 419.25, "high": 443.0, "low": 419.25, "close": 431.5, "volume": 132718}, {"timestamp": "2025-08-26T00:00:00Z", "open": 431.5, "high": 436.0, "low": 424.75, "close": 432.0, "volume": 74877}, {"timestamp": "2025-08-27T00:00:00Z", "open": 433.5, "high": 433.5, "low": 420.5, "close": 420.5, "volume": 44086}, {"timestamp": "2025-08-28T00:00:00Z", "open": 423.0, "high": 455.0, "low": 423.0, "close": 444.25, "volume": 172673}, {"timestamp": "2025-08-29T00:00:00Z", "open": 444.25, "high": 444.25, "low": 421.0, "close": 421.0, "volume": 89913}, {"timestamp": "2025-09-01T00:00:00Z", "open": 412.75, "high": 447.75, "low": 412.75, "close": 435.0, "volume": 77085}, {"timestamp": "2025-09-02T00:00:00Z", "open": 435.0, "high": 445.0, "low": 413.5, "close": 416.5, "volume": 73731}, {"timestamp": "2025-09-03T00:00:00Z", "open": 416.5, "high": 458.0, "low": 403.0, "close": 458.0, "volume": 212831}, {"timestamp": "2025-09-04T00:00:00Z", "open": 474.5, "high": 503.5, "low": 455.0, "close": 503.5, "volume": 309522}, {"timestamp": "2025-09-05T00:00:00Z", "open": 517.5, "high": 530.0, "low": 481.0, "close": 492.5, "volume": 349223}, {"timestamp": "2025-09-08T00:00:00Z", "open": 482.5, "high": 541.5, "low": 479.75, "close": 541.5, "volume": 345297}, {"timestamp": "2025-09-09T00:00:00Z", "open": 541.5, "high": 595.5, "low": 541.5, "close": 595.5, "volume": 368444}, {"timestamp": "2025-09-10T00:00:00Z", "open": 598.0, "high": 621.0, "low": 536.0, "close": 541.5, "volume": 508491}, {"timestamp": "2025-09-11T00:00:00Z", "open": 548.5, "high": 581.5, "low": 530.5, "close": 546.0, "volume": 346193}, {"timestamp": "2025-09-12T00:00:00Z", "open": 549.5, "high": 550.0, "low": 500.0, "close": 505.0, "volume": 251033}, {"timestamp": "2025-09-15T00:00:00Z", "open": 507.0, "high": 520.0, "low": 493.0, "close": 506.5, "volume": 199894}, {"timestamp": "2025-09-16T00:00:00Z", "open": 511.0, "high": 528.0, "low": 507.5, "close": 510.0, "volume": 111928}, {"timestamp": "2025-09-17T00:00:00Z", "open": 511.5, "high": 520.0, "low": 500.0, "close": 501.5, "volume": 99185}, {"timestamp": "2025-09-18T00:00:00Z", "open": 508.0, "high": 509.0, "low": 485.25, "close": 493.5, "volume": 138185}, {"timestamp": "2025-09-19T00:00:00Z", "open": 503.5, "high": 531.5, "low": 483.0, "close": 502.0, "volume": 195721}, {"timestamp": "2025-09-22T00:00:00Z", "open": 503.0, "high": 521.0, "low": 503.0, "close": 511.0, "volume": 103447}, {"timestamp": "2025-09-23T00:00:00Z", "open": 511.0, "high": 511.0, "low": 491.75, "close": 491.75, "volume": 93177}, {"timestamp": "2025-09-24T00:00:00Z", "open": 491.75, "high": 496.0, "low": 475.0, "close": 484.0, "volume": 91410}, {"timestamp": "2025-09-25T00:00:00Z", "open": 484.0, "high": 486.0, "low": 468.0, "close": 470.0, "volume": 78864}, {"timestamp": "2025-09-26T00:00:00Z", "open": 475.75, "high": 485.0, "low": 469.5, "close": 470.5, "volume": 60097}, {"timestamp": "2025-09-29T00:00:00Z", "open": 470.0, "high": 472.5, "low": 455.0, "close": 458.0, "volume": 71759}, {"timestamp": "2025-09-30T00:00:00Z", "open": 461.75, "high": 478.0, "low": 445.25, "close": 449.0, "volume": 60924}, {"timestamp": "2025-10-01T00:00:00Z", "open": 454.75, "high": 455.0, "low": 436.0, "close": 446.25, "volume": 52382}, {"timestamp": "2025-10-02T00:00:00Z", "open": 446.5, "high": 463.0, "low": 444.75, "close": 446.5, "volume": 52655}, {"timestamp": "2025-10-03T00:00:00Z", "open": 445.0, "high": 451.75, "low": 434.5, "close": 435.5, "volume": 39627}, {"timestamp": "2025-10-06T00:00:00Z", "open": 438.0, "high": 443.0, "low": 424.0, "close": 426.0, "volume": 45608}, {"timestamp": "2025-10-07T00:00:00Z", "open": 426.0, "high": 440.5, "low": 424.75, "close": 437.0, "volume": 42955}, {"timestamp": "2025-10-08T00:00:00Z", "open": 449.75, "high": 456.0, "low": 424.0, "close": 424.5, "volume": 60841}, {"timestamp": "2025-10-09T00:00:00Z", "open": 425.0, "high": 432.5, "low": 421.75, "close": 425.25, "volume": 42953}, {"timestamp": "2025-10-10T00:00:00Z", "open": 425.0, "high": 430.5, "low": 420.0, "close": 422.5, "volume": 43826}, {"timestamp": "2025-10-13T00:00:00Z", "open": 421.0, "high": 421.0, "low": 401.25, "close": 410.0, "volume": 38643}, {"timestamp": "2025-10-14T00:00:00Z", "open": 403.0, "high": 426.0, "low": 402.0, "close": 405.5, "volume": 53458}, {"timestamp": "2025-10-15T00:00:00Z", "open": 406.5, "high": 415.75, "low": 401.0, "close": 409.75, "volume": 40904}, {"timestamp": "2025-10-16T00:00:00Z", "open": 419.5, "high": 425.5, "low": 408.75, "close": 409.0, "volume": 56812}, {"timestamp": "2025-10-17T00:00:00Z", "open": 409.0, "high": 420.25, "low": 401.25, "close": 408.25, "volume": 59502}, {"timestamp": "2025-10-20T00:00:00Z", "open": 404.25, "high": 425.5, "low": 404.25, "close": 409.5, "volume": 54160}, {"timestamp": "2025-10-21T00:00:00Z", "open": 415.0, "high": 417.5, "low": 408.75, "close": 412.25, "volume": 42289}, {"timestamp": "2025-10-22T00:00:00Z", "open": 407.5, "high": 418.0, "low": 407.5, "close": 408.0, "volume": 33036}, {"timestamp": "2025-10-23T00:00:00Z", "open": 409.5, "high": 412.25, "low": 403.5, "close": 405.25, "volume": 32559}, {"timestamp": "2025-10-24T00:00:00Z", "open": 405.5, "high": 424.25, "low": 405.5, "close": 419.0, "volume": 52315}, {"timestamp": "2025-10-27T00:00:00Z", "open": 418.0, "high": 430.0, "low": 418.0, "close": 420.0, "volume": 37482}, {"timestamp": "2025-10-28T00:00:00Z", "open": 419.75, "high": 423.75, "low": 417.75, "close": 418.25, "volume": 9557}, {"timestamp": "2025-10-30T00:00:00Z", "open": 418.25, "high": 433.25, "low": 418.25, "close": 427.75, "volume": 30992}, {"timestamp": "2025-10-31T00:00:00Z", "open": 427.75, "high": 446.0, "low": 423.75, "close": 437.5, "volume": 67385}, {"timestamp": "2025-11-03T00:00:00Z", "open": 439.0, "high": 462.0, "low": 439.0, "close": 450.25, "volume": 71076}, {"timestamp": "2025-11-04T00:00:00Z", "open": 450.25, "high": 456.0, "low": 438.75, "close": 444.5, "volume": 50335}, {"timestamp": "2025-11-05T00:00:00Z", "open": 444.5, "high": 455.5, "low": 434.5, "close": 443.25, "volume": 40351}, {"timestamp": "2025-11-06T00:00:00Z", "open": 443.5, "high": 455.25, "low": 440.0, "close": 440.0, "volume": 41812}, {"timestamp": "2025-11-07T00:00:00Z", "open": 442.0, "high": 445.25, "low": 431.5, "close": 434.25, "volume": 26618}, {"timestamp": "2025-11-10T00:00:00Z", "open": 435.0, "high": 457.0, "low": 430.5, "close": 430.5, "volume": 57659}, {"timestamp": "2025-11-11T00:00:00Z", "open": 430.0, "high": 434.0, "low": 409.0, "close": 418.0, "volume": 39150}, {"timestamp": "2025-11-12T00:00:00Z", "open": 418.25, "high": 427.0, "low": 404.0, "close": 404.0, "volume": 49178}, {"timestamp": "2025-11-13T00:00:00Z", "open": 404.5, "high": 412.5, "low": 404.5, "close": 410.75, "volume": 21221}, {"timestamp": "2025-11-14T00:00:00Z", "open": 406.0, "high": 422.0, "low": 404.5, "close": 407.5, "volume": 34979}, {"timestamp": "2025-11-17T00:00:00Z", "open": 407.5, "high": 418.5, "low": 407.5, "close": 414.75, "volume": 26680}, {"timestamp": "2025-11-18T00:00:00Z", "open": 418.75, "high": 418.75, "low": 406.5, "close": 406.5, "volume": 21898}, {"timestamp": "2025-11-19T00:00:00Z", "open": 407.5, "high": 415.5, "low": 407.0, "close": 409.0, "volume": 22343}, {"timestamp": "2025-11-20T00:00:00Z", "open": 409.0, "high": 412.5, "low": 403.5, "close": 407.25, "volume": 21418}, {"timestamp": "2025-11-21T00:00:00Z", "open": 405.75, "high": 415.0, "low": 404.0, "close": 409.25, "volume": 21109}, {"timestamp": "2025-11-24T00:00:00Z", "open": 409.25, "high": 409.25, "low": 400.0, "close": 402.5, "volume": 32682}, {"timestamp": "2025-11-25T00:00:00Z", "open": 402.5, "high": 405.75, "low": 390.75, "close": 391.25, "volume": 29827}, {"timestamp": "2025-11-26T00:00:00Z", "open": 391.75, "high": 402.0, "low": 387.0, "close": 390.75, "volume": 25295}, {"timestamp": "2025-11-27T00:00:00Z", "open": 392.0, "high": 396.0, "low": 385.75, "close": 388.75, "volume": 22983}, {"timestamp": "2025-11-28T00:00:00Z", "open": 386.5, "high": 392.0, "low": 383.5, "close": 386.0, "volume": 14205}, {"timestamp": "2025-12-01T00:00:00Z", "open": 386.25, "high": 394.5, "low": 386.25, "close": 390.0, "volume": 17598}, {"timestamp": "2025-12-02T00:00:00Z", "open": 394.0, "high": 397.0, "low": 389.5, "close": 397.0, "volume": 16786}, {"timestamp": "2025-12-03T00:00:00Z", "open": 397.0, "high": 405.0, "low": 393.75, "close": 397.0, "volume": 27790}, {"timestamp": "2025-12-04T00:00:00Z", "open": 397.0, "high": 407.0, "low": 395.75, "close": 405.0, "volume": 25411}, {"timestamp": "2025-12-05T00:00:00Z", "open": 405.0, "high": 435.0, "low": 397.75, "close": 410.75, "volume": 197448}, {"timestamp": "2025-12-08T00:00:00Z", "open": 411.0, "high": 424.0, "low": 406.5, "close": 409.0, "volume": 40884}, {"timestamp": "2025-12-09T00:00:00Z", "open": 411.0, "high": 430.5, "low": 407.75, "close": 419.5, "volume": 72859}, {"timestamp": "2025-12-10T00:00:00Z", "open": 413.5, "high": 429.75, "low": 413.5, "close": 418.0, "volume": 43944}, {"timestamp": "2025-12-11T00:00:00Z", "open": 418.0, "high": 428.0, "low": 415.0, "close": 419.5, "volume": 36864}, {"timestamp": "2025-12-12T00:00:00Z", "open": 419.5, "high": 422.5, "low": 405.75, "close": 407.0, "volume": 42889}, {"timestamp": "2025-12-15T00:00:00Z", "open": 408.25, "high": 418.75, "low": 406.5, "close": 408.0, "volume": 30341}, {"timestamp": "2025-12-16T00:00:00Z", "open": 408.0, "high": 436.5, "low": 408.0, "close": 427.0, "volume": 113249}, {"timestamp": "2025-12-17T00:00:00Z", "open": 425.25, "high": 438.5, "low": 421.5, "close": 424.75, "volume": 83748}, {"timestamp": "2025-12-18T00:00:00Z", "open": 424.0, "high": 440.0, "low": 417.25, "close": 417.25, "volume": 82788}, {"timestamp": "2025-12-19T00:00:00Z", "open": 416.0, "high": 429.0, "low": 413.75, "close": 425.75, "volume": 39053}, {"timestamp": "2025-12-22T00:00:00Z", "open": 425.75, "high": 428.0, "low": 419.25, "close": 425.75, "volume": 32331}, {"timestamp": "2025-12-23T00:00:00Z", "open": 425.75, "high": 433.5, "low": 420.75, "close": 421.75, "volume": 35943}, {"timestamp": "2025-12-24T00:00:00Z", "open": 423.0, "high": 430.0, "low": 419.0, "close": 420.25, "volume": 21308}, {"timestamp": "2025-12-25T00:00:00Z", "open": 423.5, "high": 424.5, "low": 410.0, "close": 410.25, "volume": 16004}, {"timestamp": "2025-12-26T00:00:00Z", "open": 410.25, "high": 431.5, "low": 410.25, "close": 420.5, "volume": 56736}, {"timestamp": "2025-12-29T00:00:00Z", "open": 418.5, "high": 426.5, "low": 410.75, "close": 410.75, "volume": 29693}, {"timestamp": "2025-12-30T00:00:00Z", "open": 408.5, "high": 419.0, "low": 408.5, "close": 414.75, "volume": 26284}, {"timestamp": "2025-12-31T00:00:00Z", "open": 411.25, "high": 417.25, "low": 410.25, "close": 411.0, "volume": 14280}, {"timestamp": "2026-01-02T00:00:00Z", "open": 412.0, "high": 418.25, "low": 412.0, "close": 415.25, "volume": 24207}, {"timestamp": "2026-01-05T00:00:00Z", "open": 415.25, "high": 417.5, "low": 411.25, "close": 413.75, "volume": 19292}, {"timestamp": "2026-01-06T00:00:00Z", "open": 413.75, "high": 422.5, "low": 413.25, "close": 422.5, "volume": 24833}, {"timestamp": "2026-01-07T00:00:00Z", "open": 425.75, "high": 427.0, "low": 413.25, "close": 413.75, "volume": 20327}, {"timestamp": "2026-01-08T00:00:00Z", "open": 411.0, "high": 415.0, "low": 407.75, "close": 411.0, "volume": 23471}, {"timestamp": "2026-01-09T00:00:00Z", "open": 413.0, "high": 413.5, "low": 407.75, "close": 407.75, "volume": 25202}, {"timestamp": "2026-01-12T00:00:00Z", "open": 412.5, "high": 420.0, "low": 410.0, "close": 412.5, "volume": 27119}, {"timestamp": "2026-01-13T00:00:00Z", "open": 412.0, "high": 420.25, "low": 410.0, "close": 420.0, "volume": 30026}, {"timestamp": "2026-01-14T00:00:00Z", "open": 421.5, "high": 423.0, "low": 412.0, "close": 415.0, "volume": 25023}, {"timestamp": "2026-01-15T00:00:00Z", "open": 415.0, "high": 420.75, "low": 413.75, "close": 419.75, "volume": 22682}, {"timestamp": "2026-01-16T00:00:00Z", "open": 417.75, "high": 423.5, "low": 416.0, "close": 419.75, "volume": 25681}, {"timestamp": "2026-01-19T00:00:00Z", "open": 420.0, "high": 461.5, "low": 420.0, "close": 461.5, "volume": 199128}, {"timestamp": "2026-01-20T00:00:00Z", "open": 488.5, "high": 499.75, "low": 437.5, "close": 443.5, "volume": 263564}, {"timestamp": "2026-01-21T00:00:00Z", "open": 443.5, "high": 487.75, "low": 437.5, "close": 487.75, "volume": 266125}, {"timestamp": "2026-01-22T00:00:00Z", "open": 508.5, "high": 512.0, "low": 483.25, "close": 486.0, "volume": 220108}, {"timestamp": "2026-01-23T00:00:00Z", "open": 479.25, "high": 495.0, "low": 462.5, "close": 468.5, "volume": 89016}, {"timestamp": "2026-01-26T00:00:00Z", "open": 468.5, "high": 480.5, "low": 450.5, "close": 452.0, "volume": 86179}, {"timestamp": "2026-01-27T00:00:00Z", "open": 452.0, "high": 459.0, "low": 437.75, "close": 439.75, "volume": 60147}, {"timestamp": "2026-01-28T00:00:00Z", "open": 438.5, "high": 448.75, "low": 433.75, "close": 439.0, "volume": 50012}, {"timestamp": "2026-01-29T00:00:00Z", "open": 440.25, "high": 445.5, "low": 435.75, "close": 436.75, "volume": 39660}, {"timestamp": "2026-01-30T00:00:00Z", "open": 436.75, "high": 437.0, "low": 428.0, "close": 434.0, "volume": 35707}, {"timestamp": "2026-02-02T00:00:00Z", "open": 436.0, "high": 436.25, "low": 422.5, "close": 426.0, "volume": 31097}, {"timestamp": "2026-02-03T00:00:00Z", "open": 430.0, "high": 430.75, "low": 420.25, "close": 425.0, "volume": 35696}, {"timestamp": "2026-02-04T00:00:00Z", "open": 425.0, "high": 428.0, "low": 420.25, "close": 421.0, "volume": 33342}, {"timestamp": "2026-02-05T00:00:00Z", "open": 421.0, "high": 448.5, "low": 420.0, "close": 435.0, "volume": 111842}, {"timestamp": "2026-02-06T00:00:00Z", "open": 435.0, "high": 435.0, "low": 423.5, "close": 426.25, "volume": 28101}, {"timestamp": "2026-02-09T00:00:00Z", "open": 424.75, "high": 432.25, "low": 424.5, "close": 429.5, "volume": 26178}, {"timestamp": "2026-02-10T00:00:00Z", "open": 432.0, "high": 435.25, "low": 427.5, "close": 429.25, "volume": 42952}, {"timestamp": "2026-02-11T00:00:00Z", "open": 429.75, "high": 430.0, "low": 420.0, "close": 424.75, "volume": 30391}, {"timestamp": "2026-02-12T00:00:00Z", "open": 423.75, "high": 431.75, "low": 423.75, "close": 427.0, "volume": 26054}, {"timestamp": "2026-02-13T00:00:00Z", "open": 429.0, "high": 431.0, "low": 424.5, "close": 425.0, "volume": 43859}, {"timestamp": "2026-02-16T00:00:00Z", "open": 425.5, "high": 442.5, "low": 425.5, "close": 435.5, "volume": 54063}, {"timestamp": "2026-02-17T00:00:00Z", "open": 435.5, "high": 438.0, "low": 427.5, "close": 430.75, "volume": 41192}, {"timestamp": "2026-02-18T00:00:00Z", "open": 434.0, "high": 451.25, "low": 429.0, "close": 442.25, "volume": 113564}, {"timestamp": "2026-02-19T00:00:00Z", "open": 449.5, "high": 461.0, "low": 416.25, "close": 418.25, "volume": 105242}, {"timestamp": "2026-02-20T00:00:00Z", "open": 424.25, "high": 424.25, "low": 412.0, "close": 417.5, "volume": 45604}, {"timestamp": "2026-02-23T00:00:00Z", "open": 418.25, "high": 429.75, "low": 417.0, "close": 417.0, "volume": 25484}, {"timestamp": "2026-02-24T00:00:00Z", "open": 420.0, "high": 420.0, "low": 400.75, "close": 408.0, "volume": 36827}, {"timestamp": "2026-02-25T00:00:00Z", "open": 408.0, "high": 408.0, "low": 395.0, "close": 395.25, "volume": 36935}, {"timestamp": "2026-02-26T00:00:00Z", "open": 396.0, "high": 401.0, "low": 390.25, "close": 393.0, "volume": 51773}, {"timestamp": "2026-02-27T00:00:00Z", "open": 393.0, "high": 407.0, "low": 391.0, "close": 394.0, "volume": 36815}]