[{"timestamp": "2025-02-27T00:00:00Z", "open": 3.0, "high": 3.04, "low": 2.96, "close": 3.01, "volume": 23065040}, {"timestamp": "2025-02-28T00:00:00Z", "open": 3.01, "high": 3.05, "low": 2.99, "close": 3.02, "volume": 13742370}, {"timestamp": "2025-03-03T00:00:00Z", "open": 3.04, "high": 3.07, "low": 2.99, "close": 3.0, "volume": 22216100}, {"timestamp": "2025-03-04T00:00:00Z", "open": 3.0, "high": 3.0, "low": 2.8, "close": 2.84, "volume": 28722930}, {"timestamp": "2025-03-05T00:00:00Z", "open": 2.85, "high": 3.1, "low": 2.83, "close": 3.04, "volume": 65853920}, {"timestamp": "2025-03-06T00:00:00Z", "open": 3.05, "high": 3.17, "low": 2.94, "close": 3.08, "volume": 35105890}, {"timestamp": "2025-03-07T00:00:00Z", "open": 3.08, "high": 3.23, "low": 3.04, "close": 3.2, "volume": 36939420}, {"timestamp": "2025-03-10T00:00:00Z", "open": 3.2, "high": 3.27, "low": 3.18, "close": 3.23, "volume": 22029060}, {"timestamp": "2025-03-11T00:00:00Z", "open": 3.17, "high": 3.22, "low": 3.11, "close": 3.17, "volume": 20338630}, {"timestamp": "2025-03-12T00:00:00Z", "open": 3.17, "high": 3.39, "low": 3.13, "close": 3.25, "volume": 73710640}, {"timestamp": "2025-03-13T00:00:00Z", "open": 3.25, "high": 3.36, "low": 3.25, "close": 3.29, "volume": 28351610}, {"timestamp": "2025-03-14T00:00:00Z", "open": 3.3, "high": 3.33, "low": 3.27, "close": 3.27, "volume": 27557890}, {"timestamp": "2025-03-17T00:00:00Z", "open": 3.31, "high": 3.36, "low": 3.29, "close": 3.33, "volume": 32288080}, {"timestamp": "2025-03-18T00:00:00Z", "open": 3.33, "high": 3.34, "low": 3.22, "close": 3.28, "volume": 24126250}, {"timestamp": "2025-03-19T00:00:00Z", "open": 3.1, "high": 3.15, "low": 2.95, "close": 2.95, "volume": 24260090}, {"timestamp": "2025-03-20T00:00:00Z", "open": 2.96, "high": 3.12, "low": 2.89, "close": 2.96, "volume": 24440810}, {"timestamp": "2025-03-21T00:00:00Z", "open": 2.96, "high": 2.96, "low": 2.66, "close": 2.7, "volume": 20233470}, {"timestamp": "2025-03-24T00:00:00Z", "open": 2.69, "high": 2.81, "low": 2.56, "close": 2.72, "volume": 21858660}, {"timestamp": "2025-03-25T00:00:00Z", "open": 2.79, "high": 2.85, "low": 2.74, "close": 2.83, "volume": 17345230}, {"timestamp": "2025-03-26T00:00:00Z", "open": 2.83, "high": 2.87, "low": 2.71, "close": 2.85, "volume": 18340410}, {"timestamp": "2025-03-27T00:00:00Z", "open": 2.9, "high": 2.99, "low": 2.81, "close": 2.87, "volume": 22233120}, {"timestamp": "2025-03-28T00:00:00Z", "open": 2.87, "high": 2.9, "low": 2.77, "close": 2.9, "volume": 15178260}, {"timestamp": "2025-04-02T00:00:00Z", "open": 2.9, "high": 2.98, "low": 2.85, "close": 2.92, "volume": 21461950}, {"timestamp": "2025-04-03T00:00:00Z", "open": 2.92, "high": 2.97, "low": 2.88, "close": 2.88, "volume": 20472660}, {"timestamp": "2025-04-04T00:00:00Z", "open": 2.9, "high": 2.9, "low": 2.82, "close": 2.83, "volume": 13023110}, {"timestamp": "2025-04-07T00:00:00Z", "open": 2.8, "high": 2.84, "low": 2.7, "close": 2.82, "volume": 13501430}, {"timestamp": "2025-04-08T00:00:00Z", "open": 2.83, "high": 2.88, "low": 2.83, "close": 2.85, "volume": 10570720}, {"timestamp": "2025-04-09T00:00:00Z", "open": 2.84, "high": 2.99, "low": 2.75, "close": 2.84, "volume": 32001810}, {"timestamp": "2025-04-10T00:00:00Z", "open": 2.95, "high": 2.96, "low": 2.86, "close": 2.86, "volume": 11235990}, {"timestamp": "2025-04-11T00:00:00Z", "open": 2.86, "high": 3.1, "low": 2.8, "close": 2.94, "volume": 70717780}, {"timestamp": "2025-04-14T00:00:00Z", "open": 2.95, "high": 3.02, "low": 2.93, "close": 2.93, "volume": 28523960}, {"timestamp": "2025-04-15T00:00:00Z", "open": 2.93, "high": 2.94, "low": 2.88, "close": 2.9, "volume": 20002590}, {"timestamp": "2025-04-16T00:00:00Z", "open": 2.9, "high": 2.91, "low": 2.82, "close": 2.83, "volume": 12164980}, {"timestamp": "2025-04-17T00:00:00Z", "open": 2.83, "high": 3.01, "low": 2.75, "close": 2.93, "volume": 67626370}, {"timestamp": "2025-04-18T00:00:00Z", "open": 3.0, "high": 3.17, "low": 2.91, "close": 3.06, "volume": 102431900}, {"timestamp": "2025-04-21T00:00:00Z", "open": 3.09, "high": 3.25, "low": 3.09, "close": 3.21, "volume": 65838630}, {"timestamp": "2025-04-22T00:00:00Z", "open": 3.3, "high": 3.34, "low": 3.2, "close": 3.25, "volume": 75407320}, {"timestamp": "2025-04-24T00:00:00Z", "open": 3.25, "high": 3.36, "low": 3.15, "close": 3.31, "volume": 98017340}, {"timestamp": "2025-04-25T00:00:00Z", "open": 3.32, "high": 3.33, "low": 3.26, "close": 3.31, "volume": 35020160}, {"timestamp": "2025-04-28T00:00:00Z", "open": 3.37, "high": 3.51, "low": 3.31, "close": 3.51, "volume": 82006660}, {"timestamp": "2025-04-29T00:00:00Z", "open": 3.54, "high": 3.55, "low": 3.26, "close": 3.4, "volume": 99634630}, {"timestamp": "2025-04-30T00:00:00Z", "open": 3.49, "high": 3.52, "low": 3.33, "close": 3.4, "volume": 101800800}, {"timestamp": "2025-05-02T00:00:00Z", "open": 3.41, "high": 3.53, "low": 3.39, "close": 3.44, "volume": 49590930}, {"timestamp": "2025-05-05T00:00:00Z", "open": 3.5, "high": 3.64, "low": 3.45, "close": 3.61, "volume": 134412400}, {"timestamp": "2025-05-06T00:00:00Z", "open": 3.63, "high": 3.75, "low": 3.56, "close": 3.65, "volume": 113181300}, {"timestamp": "2025-05-07T00:00:00Z", "open": 3.65, "high": 3.68, "low": 3.53, "close": 3.53, "volume": 106968100}, {"timestamp": "2025-05-08T00:00:00Z", "open": 3.54, "high": 3.58, "low": 3.43, "close": 3.47, "volume": 51087080}, {"timestamp": "2025-05-09T00:00:00Z", "open": 3.46, "high": 3.47, "low": 3.35, "close": 3.37, "volume": 34899990}, {"timestamp": "2025-05-12T00:00:00Z", "open": 3.39, "high": 3.57, "low": 3.37, "close": 3.51, "volume": 53580020}, {"timestamp": "2025-05-13T00:00:00Z", "open": 3.5, "high": 3.5, "low": 3.3, "close": 3.44, "volume": 73006440}, {"timestamp": "2025-05-14T00:00:00Z", "open": 3.5, "high": 3.54, "low": 3.45, "close": 3.45, "volume": 33895360}, {"timestamp": "2025-05-15T00:00:00Z", "open": 3.45, "high": 3.48, "low": 3.35, "close": 3.35, "volume": 30888410}, {"timestamp": "2025-05-16T00:00:00Z", "open": 3.4, "high": 3.42, "low": 3.34, "close": 3.36, "volume": 24608450}, {"timestamp": "2025-05-20T00:00:00Z", "open": 3.36, "high": 3.4, "low": 3.16, "close": 3.16, "volume": 24120380}, {"timestamp": "2025-05-21T00:00:00Z", "open": 3.2, "high": 3.48, "low": 3.19, "close": 3.32, "volume": 153583000}, {"timestamp": "2025-05-22T00:00:00Z", "open": 3.32, "high": 3.37, "low": 3.22, "close": 3.26, "volume": 51653450}, {"timestamp": "2025-05-23T00:00:00Z", "open": 3.25, "high": 3.29, "low": 3.2, "close": 3.2, "volume": 31058280}, {"timestamp": "2025-05-26T00:00:00Z", "open": 3.21, "high": 3.3, "low": 3.12, "close": 3.2, "volume": 42023750}, {"timestamp": "2025-05-27T00:00:00Z", "open": 3.19, "high": 3.21, "low": 3.11, "close": 3.11, "volume": 18141730}, {"timestamp": "2025-05-28T00:00:00Z", "open": 3.1, "high": 3.14, "low": 2.98, "close": 2.98, "volume": 17178760}, {"timestamp": "2025-05-29T00:00:00Z", "open": 3.01, "high": 3.03, "low": 2.91, "close": 2.92, "volume": 19464180}, {"timestamp": "2025-05-30T00:00:00Z", "open": 2.89, "high": 2.98, "low": 2.83, "close": 2.84, "volume": 28760880}, {"timestamp": "2025-06-02T00:00:00Z", "open": 2.86, "high": 2.86, "low": 2.79, "close": 2.8, "volume": 14495440}, {"timestamp": "2025-06-03T00:00:00Z", "open": 2.8, "high": 2.88, "low": 2.8, "close": 2.84, "volume": 13932170}, {"timestamp": "2025-06-04T00:00:00Z", "open": 2.89, "high": 3.1, "low": 2.84, "close": 2.97, "volume": 63228010}, {"timestamp": "2025-06-05T00:00:00Z", "open": 2.98, "high": 3.0, "low": 2.94, "close": 2.98, "volume": 8748490}, {"timestamp": "2025-06-10T00:00:00Z", "open": 2.98, "high": 3.11, "low": 2.98, "close": 3.04, "volume": 22628170}, {"timestamp": "2025-06-11T00:00:00Z", "open": 3.04, "high": 3.09, "low": 3.01, "close": 3.06, "volume": 24236600}, {"timestamp": "2025-06-12T00:00:00Z", "open": 3.05, "high": 3.1, "low": 2.99, "close": 2.99, "volume": 38336310}, {"timestamp": "2025-06-13T00:00:00Z", "open": 2.94, "high": 2.94, "low": 2.76, "close": 2.83, "volume": 21929370}, {"timestamp": "2025-06-16T00:00:00Z", "open": 2.81, "high": 2.94, "low": 2.79, "close": 2.88, "volume": 31846750}, {"timestamp": "2025-06-17T00:00:00Z", "open": 2.88, "high": 3.02, "low": 2.88, "close": 2.97, "volume": 71361050}, {"timestamp": "2025-06-18T00:00:00Z", "open": 2.97, "high": 2.97, "low": 2.86, "close": 2.9, "volume": 31051130}, {"timestamp": "2025-06-19T00:00:00Z", "open": 2.93, "high": 3.05, "low": 2.89, "close": 2.98, "volume": 46932450}, {"timestamp": "2025-06-20T00:00:00Z", "open": 2.99, "high": 3.02, "low": 2.93, "close": 2.99, "volume": 22295080}, {"timestamp": "2025-06-23T00:00:00Z", "open": 2.98, "high": 2.98, "low": 2.85, "close": 2.91, "volume": 15892310}, {"timestamp": "2025-06-24T00:00:00Z", "open": 3.05, "high": 3.05, "low": 2.95, "close": 3.03, "volume": 40108980}, {"timestamp": "2025-06-25T00:00:00Z", "open": 3.03, "high": 3.05, "low": 2.75, "close": 2.75, "volume": 113175200}, {"timestamp": "2025-06-26T00:00:00Z", "open": 2.76, "high": 2.79, "low": 2.63, "close": 2.67, "volume": 102569100}, {"timestamp": "2025-06-27T00:00:00Z", "open": 2.68, "high": 2.75, "low": 2.66, "close": 2.67, "volume": 40078600}, {"timestamp": "2025-06-30T00:00:00Z", "open": 2.67, "high": 2.73, "low": 2.67, "close": 2.71, "volume": 36154630}, {"timestamp": "2025-07-01T00:00:00Z", "open": 2.72, "high": 2.75, "low": 2.7, "close": 2.72, "volume": 29845030}, {"timestamp": "2025-07-02T00:00:00Z", "open": 2.74, "high": 2.78, "low": 2.72, "close": 2.73, "volume": 34152900}, {"timestamp": "2025-07-03T00:00:00Z", "open": 2.75, "high": 2.76, "low": 2.73, "close": 2.74, "volume": 23892530}, {"timestamp": "2025-07-04T00:00:00Z", "open": 2.74, "high": 2.81, "low": 2.73, "close": 2.78, "volume": 40098980}, {"timestamp": "2025-07-07T00:00:00Z", "open": 2.77, "high": 2.77, "low": 2.71, "close": 2.73, "volume": 16581610}, {"timestamp": "2025-07-08T00:00:00Z", "open": 2.73, "high": 2.75, "low": 2.68, "close": 2.7, "volume": 21834300}, {"timestamp": "2025-07-09T00:00:00Z", "open": 2.74, "high": 2.76, "low": 2.72, "close": 2.72, "volume": 22207800}, {"timestamp": "2025-07-10T00:00:00Z", "open": 2.76, "high": 2.79, "low": 2.75, "close": 2.76, "volume": 33133530}, {"timestamp": "2025-07-11T00:00:00Z", "open": 2.77, "high": 2.79, "low": 2.72, "close": 2.75, "volume": 24129190}, {"timestamp": "2025-07-14T00:00:00Z", "open": 2.75, "high": 2.85, "low": 2.74, "close": 2.81, "volume": 40747600}, {"timestamp": "2025-07-16T00:00:00Z", "open": 2.81, "high": 2.85, "low": 2.71, "close": 2.75, "volume": 46407260}, {"timestamp": "2025-07-17T00:00:00Z", "open": 2.77, "high": 2.81, "low": 2.76, "close": 2.78, "volume": 57233700}, {"timestamp": "2025-07-18T00:00:00Z", "open": 2.78, "high": 2.79, "low": 2.74, "close": 2.76, "volume": 34847460}, {"timestamp": "2025-07-21T00:00:00Z", "open": 2.77, "high": 2.84, "low": 2.77, "close": 2.81, "volume": 51200970}, {"timestamp": "2025-07-22T00:00:00Z", "open": 2.81, "high": 2.82, "low": 2.73, "close": 2.74, "volume": 136919700}, {"timestamp": "2025-07-23T00:00:00Z", "open": 2.75, "high": 2.77, "low": 2.74, "close": 2.75, "volume": 44543300}, {"timestamp": "2025-07-24T00:00:00Z", "open": 2.75, "high": 2.82, "low": 2.75, "close": 2.8, "volume": 65659030}, {"timestamp": "2025-07-25T00:00:00Z", "open": 2.81, "high": 2.89, "low": 2.76, "close": 2.88, "volume": 118559900}, {"timestamp": "2025-07-28T00:00:00Z", "open": 2.9, "high": 2.98, "low": 2.89, "close": 2.93, "volume": 80274610}, {"timestamp": "2025-07-29T00:00:00Z", "open": 3.0, "high": 3.01, "low": 2.89, "close": 2.9, "volume": 59783090}, {"timestamp": "2025-07-30T00:00:00Z", "open": 2.91, "high": 2.96, "low": 2.87, "close": 2.91, "volume": 64846860}, {"timestamp": "2025-07-31T00:00:00Z", "open": 2.92, "high": 2.98, "low": 2.91, "close": 2.94, "volume": 64307480}, {"timestamp": "2025-08-01T00:00:00Z", "open": 2.95, "high": 2.95, "low": 2.91, "close": 2.93, "volume": 38022840}, {"timestamp": "2025-08-04T00:00:00Z", "open": 2.93, "high": 3.09, "low": 2.93, "close": 3.08, "volume": 109387400}, {"timestamp": "2025-08-05T00:00:00Z", "open": 3.08, "high": 3.22, "low": 3.03, "close": 3.13, "volume": 105037500}, {"timestamp": "2025-08-06T00:00:00Z", "open": 3.13, "high": 3.35, "low": 3.13, "close": 3.27, "volume": 101235600}, {"timestamp": "2025-08-07T00:00:00Z", "open": 3.28, "high": 3.34, "low": 3.22, "close": 3.22, "volume": 70654660}, {"timestamp": "2025-08-08T00:00:00Z", "open": 3.22, "high": 3.25, "low": 3.13, "close": 3.16, "volume": 45544470}, {"timestamp": "2025-08-11T00:00:00Z", "open": 3.17, "high": 3.22, "low": 3.15, "close": 3.17, "volume": 35836800}, {"timestamp": "2025-08-12T00:00:00Z", "open": 3.17, "high": 3.38, "low": 3.1, "close": 3.31, "volume": 239055100}, {"timestamp": "2025-08-13T00:00:00Z", "open": 3.31, "high": 3.31, "low": 3.21, "close": 3.23, "volume": 48823700}, {"timestamp": "2025-08-14T00:00:00Z", "open": 3.21, "high": 3.23, "low": 3.11, "close": 3.11, "volume": 38507630}, {"timestamp": "2025-08-15T00:00:00Z", "open": 3.25, "high": 3.42, "low": 3.16, "close": 3.42, "volume": 185193200}, {"timestamp": "2025-08-18T00:00:00Z", "open": 3.5, "high": 3.66, "low": 3.42, "close": 3.55, "volume": 170675100}, {"timestamp": "2025-08-19T00:00:00Z", "open": 3.59, "high": 3.76, "low": 3.42, "close": 3.64, "volume": 134036000}, {"timestamp": "2025-08-20T00:00:00Z", "open": 3.68, "high": 3.71, "low": 3.48, "close": 3.49, "volume": 109460300}, {"timestamp": "2025-08-21T00:00:00Z", "open": 3.49, "high": 3.56, "low": 3.42, "close": 3.5, "volume": 117773100}, {"timestamp": "2025-08-22T00:00:00Z", "open": 3.51, "high": 3.76, "low": 3.5, "close": 3.7, "volume": 133458600}, {"timestamp": "2025-08-25T00:00:00Z", "open": 3.72, "high": 4.07, "low": 3.65, "close": 4.07, "volume": 179411900}, {"timestamp": "2025-08-26T00:00:00Z", "open": 4.1, "high": 4.23, "low": 3.84, "close": 3.91, "volume": 152983100}, {"timestamp": "2025-08-27T00:00:00Z", "open": 3.97, "high": 4.0, "low": 3.52, "close": 3.55, "volume": 216296700}, {"timestamp": "2025-08-28T00:00:00Z", "open": 3.55, "high": 3.61, "low": 3.22, "close": 3.34, "volume": 437000400}, {"timestamp": "2025-08-29T00:00:00Z", "open": 3.36, "high": 3.42, "low": 3.25, "close": 3.27, "volume": 90099920}, {"timestamp": "2025-09-01T00:00:00Z", "open": 3.27, "high": 3.34, "low": 3.22, "close": 3.28, "volume": 63791620}, {"timestamp": "2025-09-02T00:00:00Z", "open": 3.33, "high": 3.47, "low": 3.17, "close": 3.33, "volume": 197256800}, {"timestamp": "2025-09-03T00:00:00Z", "open": 3.33, "high": 3.36, "low": 3.26, "close": 3.33, "volume": 65231680}, {"timestamp": "2025-09-04T00:00:00Z", "open": 3.33, "high": 3.36, "low": 3.28, "close": 3.3, "volume": 55609180}, {"timestamp": "2025-09-05T00:00:00Z", "open": 3.32, "high": 3.47, "low": 3.16, "close": 3.3, "volume": 139803500}, {"timestamp": "2025-09-08T00:00:00Z", "open": 3.2, "high": 3.25, "low": 3.15, "close": 3.16, "volume": 45008590}, {"timestamp": "2025-09-09T00:00:00Z", "open": 3.18, "high": 3.22, "low": 3.15, "close": 3.16, "volume": 46009200}, {"timestamp": "2025-09-10T00:00:00Z", "open": 3.16, "high": 3.18, "low": 3.1, "close": 3.11, "volume": 29306460}, {"timestamp": "2025-09-11T00:00:00Z", "open": 3.1, "high": 3.13, "low": 2.98, "close": 2.99, "volume": 53734370}, {"timestamp": "2025-09-12T00:00:00Z", "open": 2.99, "high": 3.0, "low": 2.9, "close": 2.93, "volume": 33060040}, {"timestamp": "2025-09-15T00:00:00Z", "open": 2.95, "high": 3.16, "low": 2.89, "close": 3.15, "volume": 53180860}, {"timestamp": "2025-09-16T00:00:00Z", "open": 3.16, "high": 3.25, "low": 3.13, "close": 3.24, "volume": 54775300}, {"timestamp": "2025-09-17T00:00:00Z", "open": 3.24, "high": 3.28, "low": 3.2, "close": 3.25, "volume": 42025560}, {"timestamp": "2025-09-18T00:00:00Z", "open": 3.25, "high": 3.37, "low": 3.24, "close": 3.31, "volume": 69826150}, {"timestamp": "2025-09-19T00:00:00Z", "open": 3.31, "high": 3.33, "low": 3.26, "close": 3.33, "volume": 46064620}, {"timestamp": "2025-09-22T00:00:00Z", "open": 3.37, "high": 3.49, "low": 3.35, "close": 3.4, "volume": 76791050}, {"timestamp": "2025-09-23T00:00:00Z", "open": 3.38, "high": 3.45, "low": 3.3, "close": 3.37, "volume": 97738650}, {"timestamp": "2025-09-24T00:00:00Z", "open": 3.37, "high": 3.42, "low": 3.32, "close": 3.37, "volume": 54446890}, {"timestamp": "2025-09-25T00:00:00Z", "open": 3.38, "high": 3.39, "low": 3.27, "close": 3.32, "volume": 24543780}, {"timestamp": "2025-09-26T00:00:00Z", "open": 3.34, "high": 3.34, "low": 3.17, "close": 3.18, "volume": 46078120}, {"timestamp": "2025-09-29T00:00:00Z", "open": 3.18, "high": 3.23, "low": 3.13, "close": 3.13, "volume": 32203940}, {"timestamp": "2025-09-30T00:00:00Z", "open": 3.14, "high": 3.16, "low": 2.99, "close": 3.03, "volume": 66041620}, {"timestamp": "2025-10-01T00:00:00Z", "open": 3.07, "high": 3.07, "low": 2.91, "close": 3.0, "volume": 61230980}, {"timestamp": "2025-10-02T00:00:00Z", "open": 3.01, "high": 3.08, "low": 2.86, "close": 2.92, "volume": 135904800}, {"timestamp": "2025-10-03T00:00:00Z", "open": 2.92, "high": 2.93, "low": 2.88, "close": 2.89, "volume": 35312900}, {"timestamp": "2025-10-06T00:00:00Z", "open": 2.96, "high": 2.96, "low": 2.89, "close": 2.9, "volume": 39036020}, {"timestamp": "2025-10-07T00:00:00Z", "open": 2.91, "high": 2.95, "low": 2.87, "close": 2.93, "volume": 39790510}, {"timestamp": "2025-10-08T00:00:00Z", "open": 2.91, "high": 2.95, "low": 2.89, "close": 2.9, "volume": 35315580}, {"timestamp": "2025-10-09T00:00:00Z", "open": 2.91, "high": 2.95, "low": 2.87, "close": 2.88, "volume": 33464110}, {"timestamp": "2025-10-10T00:00:00Z", "open": 2.89, "high": 2.91, "low": 2.88, "close": 2.9, "volume": 23555560}, {"timestamp": "2025-10-13T00:00:00Z", "open": 2.83, "high": 2.89, "low": 2.78, "close": 2.8, "volume": 33112380}, {"timestamp": "2025-10-14T00:00:00Z", "open": 2.81, "high": 2.83, "low": 2.73, "close": 2.73, "volume": 37227020}, {"timestamp": "2025-10-15T00:00:00Z", "open": 2.76, "high": 2.87, "low": 2.75, "close": 2.87, "volume": 47921350}, {"timestamp": "2025-10-16T00:00:00Z", "open": 2.87, "high": 2.89, "low": 2.79, "close": 2.8, "volume": 33977510}, {"timestamp": "2025-10-17T00:00:00Z", "open": 2.8, "high": 2.82, "low": 2.72, "close": 2.77, "volume": 40090070}, {"timestamp": "2025-10-20T00:00:00Z", "open": 2.78, "high": 2.84, "low": 2.75, "close": 2.83, "volume": 40649760}, {"timestamp": "2025-10-21T00:00:00Z", "open": 2.85, "high": 2.97, "low": 2.81, "close": 2.92, "volume": 74327350}, {"timestamp": "2025-10-22T00:00:00Z", "open": 2.92, "high": 2.94, "low": 2.88, "close": 2.89, "volume": 28598160}, {"timestamp": "2025-10-23T00:00:00Z", "open": 2.89, "high": 2.91, "low": 2.76, "close": 2.77, "volume": 51029840}, {"timestamp": "2025-10-24T00:00:00Z", "open": 2.78, "high": 2.84, "low": 2.73, "close": 2.82, "volume": 83309710}, {"timestamp": "2025-10-27T00:00:00Z", "open": 2.82, "high": 2.92, "low": 2.72, "close": 2.72, "volume": 251850500}, {"timestamp": "2025-10-28T00:00:00Z", "open": 2.72, "high": 2.74, "low": 2.62, "close": 2.68, "volume": 103463300}, {"timestamp": "2025-10-30T00:00:00Z", "open": 2.69, "high": 2.78, "low": 2.69, "close": 2.77, "volume": 90133800}, {"timestamp": "2025-10-31T00:00:00Z", "open": 2.79, "high": 2.86, "low": 2.72, "close": 2.85, "volume": 79452030}, {"timestamp": "2025-11-03T00:00:00Z", "open": 2.88, "high": 2.95, "low": 2.87, "close": 2.95, "volume": 73612980}, {"timestamp": "2025-11-04T00:00:00Z", "open": 2.95, "high": 2.95, "low": 2.86, "close": 2.88, "volume": 51295400}, {"timestamp": "2025-11-05T00:00:00Z", "open": 2.87, "high": 2.91, "low": 2.81, "close": 2.87, "volume": 62493220}, {"timestamp": "2025-11-06T00:00:00Z", "open": 2.86, "high": 2.91, "low": 2.86, "close": 2.89, "volume": 38156880}, {"timestamp": "2025-11-07T00:00:00Z", "open": 2.89, "high": 2.89, "low": 2.77, "close": 2.78, "volume": 52626800}, {"timestamp": "2025-11-10T00:00:00Z", "open": 2.78, "high": 2.82, "low": 2.75, "close": 2.81, "volume": 46332400}, {"timestamp": "2025-11-11T00:00:00Z", "open": 2.7, "high": 2.76, "low": 2.57, "close": 2.66, "volume": 88538690}, {"timestamp": "2025-11-12T00:00:00Z", "open": 2.69, "high": 2.69, "low": 2.62, "close": 2.67, "volume": 42837370}, {"timestamp": "2025-11-13T00:00:00Z", "open": 2.68, "high": 2.68, "low": 2.63, "close": 2.63, "volume": 29392150}, {"timestamp": "2025-11-14T00:00:00Z", "open": 2.63, "high": 2.63, "low": 2.58, "close": 2.6, "volume": 30988330}, {"timestamp": "2025-11-17T00:00:00Z", "open": 2.61, "high": 2.66, "low": 2.6, "close": 2.64, "volume": 44252450}, {"timestamp": "2025-11-18T00:00:00Z", "open": 2.65, "high": 2.72, "low": 2.63, "close": 2.64, "volume": 61111880}, {"timestamp": "2025-11-19T00:00:00Z", "open": 2.66, "high": 2.76, "low": 2.65, "close": 2.71, "volume": 100132600}, {"timestamp": "2025-11-20T00:00:00Z", "open": 2.72, "high": 2.75, "low": 2.63, "close": 2.66, "volume": 73236360}, {"timestamp": "2025-11-21T00:00:00Z", "open": 2.65, "high": 2.65, "low": 2.55, "close": 2.58, "volume": 163357700}, {"timestamp": "2025-11-24T00:00:00Z", "open": 2.59, "high": 2.6, "low": 2.51, "close": 2.52, "volume": 80375720}, {"timestamp": "2025-11-25T00:00:00Z", "open": 2.53, "high": 2.53, "low": 2.43, "close": 2.44, "volume": 70323780}, {"timestamp": "2025-11-26T00:00:00Z", "open": 2.44, "high": 2.46, "low": 2.37, "close": 2.38, "volume": 46267640}, {"timestamp": "2025-11-27T00:00:00Z", "open": 2.39, "high": 2.4, "low": 2.36, "close": 2.36, "volume": 40387870}, {"timestamp": "2025-11-28T00:00:00Z", "open": 2.36, "high": 2.41, "low": 2.35, "close": 2.38, "volume": 39792220}, {"timestamp": "2025-12-01T00:00:00Z", "open": 2.39, "high": 2.43, "low": 2.39, "close": 2.42, "volume": 40327050}, {"timestamp": "2025-12-02T00:00:00Z", "open": 2.42, "high": 2.51, "low": 2.4, "close": 2.45, "volume": 73954400}, {"timestamp": "2025-12-03T00:00:00Z", "open": 2.47, "high": 2.55, "low": 2.42, "close": 2.54, "volume": 80410550}, {"timestamp": "2025-12-04T00:00:00Z", "open": 2.54, "high": 2.58, "low": 2.47, "close": 2.48, "volume": 68460850}, {"timestamp": "2025-12-05T00:00:00Z", "open": 2.48, "high": 2.49, "low": 2.44, "close": 2.45, "volume": 29529630}, {"timestamp": "2025-12-08T00:00:00Z", "open": 2.47, "high": 2.48, "low": 2.45, "close": 2.45, "volume": 26505780}, {"timestamp": "2025-12-09T00:00:00Z", "open": 2.46, "high": 2.47, "low": 2.44, "close": 2.44, "volume": 22378020}, {"timestamp": "2025-12-10T00:00:00Z", "open": 2.44, "high": 2.46, "low": 2.4, "close": 2.4, "volume": 29366600}, {"timestamp": "2025-12-11T00:00:00Z", "open": 2.4, "high": 2.43, "low": 2.4, "close": 2.41, "volume": 23303600}, {"timestamp": "2025-12-12T00:00:00Z", "open": 2.42, "high": 2.47, "low": 2.41, "close": 2.43, "volume": 32672080}, {"timestamp": "2025-12-15T00:00:00Z", "open": 2.43, "high": 2.48, "low": 2.43, "close": 2.48, "volume": 29184050}, {"timestamp": "2025-12-16T00:00:00Z", "open": 2.48, "high": 2.5, "low": 2.45, "close": 2.46, "volume": 23846410}, {"timestamp": "2025-12-17T00:00:00Z", "open": 2.46, "high": 2.49, "low": 2.45, "close": 2.45, "volume": 20232340}, {"timestamp": "2025-12-18T00:00:00Z", "open": 2.48, "high": 2.7, "low": 2.47, "close": 2.7, "volume": 191265000}, {"timestamp": "2025-12-19T00:00:00Z", "open": 2.72, "high": 2.74, "low": 2.58, "close": 2.63, "volume": 134647200}, {"timestamp": "2025-12-22T00:00:00Z", "open": 2.64, "high": 2.65, "low": 2.54, "close": 2.56, "volume": 74640940}, {"timestamp": "2025-12-23T00:00:00Z", "open": 2.57, "high": 2.74, "low": 2.56, "close": 2.62, "volume": 135698900}, {"timestamp": "2025-12-24T00:00:00Z", "open": 2.62, "high": 2.65, "low": 2.58, "close": 2.59, "volume": 49684980}, {"timestamp": "2025-12-25T00:00:00Z", "open": 2.65, "high": 2.69, "low": 2.62, "close": 2.66, "volume": 54377470}, {"timestamp": "2025-12-26T00:00:00Z", "open": 2.65, "high": 2.66, "low": 2.6, "close": 2.62, "volume": 30734060}, {"timestamp": "2025-12-29T00:00:00Z", "open": 2.63, "high": 2.66, "low": 2.54, "close": 2.55, "volume": 33502850}, {"timestamp": "2025-12-30T00:00:00Z", "open": 2.57, "high": 2.57, "low": 2.52, "close": 2.53, "volume": 23662180}, {"timestamp": "2025-12-31T00:00:00Z", "open": 2.54, "high": 2.58, "low": 2.54, "close": 2.57, "volume": 22296290}, {"timestamp": "2026-01-02T00:00:00Z", "open": 2.57, "high": 2.67, "low": 2.56, "close": 2.65, "volume": 46145880}, {"timestamp": "2026-01-05T00:00:00Z", "open": 2.65, "high": 2.66, "low": 2.61, "close": 2.65, "volume": 41552220}, {"timestamp": "2026-01-06T00:00:00Z", "open": 2.72, "high": 2.78, "low": 2.7, "close": 2.71, "volume": 80595210}, {"timestamp": "2026-01-07T00:00:00Z", "open": 2.71, "high": 2.73, "low": 2.62, "close": 2.63, "volume": 43821040}, {"timestamp": "2026-01-08T00:00:00Z", "open": 2.63, "high": 2.68, "low": 2.58, "close": 2.64, "volume": 48140470}, {"timestamp": "2026-01-09T00:00:00Z", "open": 2.64, "high": 2.65, "low": 2.61, "close": 2.61, "volume": 29964640}, {"timestamp": "2026-01-12T00:00:00Z", "open": 2.61, "high": 2.66, "low": 2.59, "close": 2.62, "volume": 44010010}, {"timestamp": "2026-01-13T00:00:00Z", "open": 2.62, "high": 2.68, "low": 2.6, "close": 2.67, "volume": 58952120}, {"timestamp": "2026-01-14T00:00:00Z", "open": 2.67, "high": 2.78, "low": 2.64, "close": 2.74, "volume": 104071400}, {"timestamp": "2026-01-15T00:00:00Z", "open": 2.74, "high": 2.96, "low": 2.72, "close": 2.95, "volume": 132406800}, {"timestamp": "2026-01-16T00:00:00Z", "open": 3.09, "high": 3.16, "low": 2.98, "close": 3.01, "volume": 202836300}, {"timestamp": "2026-01-19T00:00:00Z", "open": 3.07, "high": 3.31, "low": 3.03, "close": 3.17, "volume": 286193200}, {"timestamp": "2026-01-20T00:00:00Z", "open": 3.23, "high": 3.47, "low": 3.07, "close": 3.35, "volume": 270245500}, {"timestamp": "2026-01-21T00:00:00Z", "open": 3.4, "high": 3.56, "low": 3.18, "close": 3.42, "volume": 196368300}, {"timestamp": "2026-01-22T00:00:00Z", "open": 3.42, "high": 3.51, "low": 3.26, "close": 3.3, "volume": 132245800}, {"timestamp": "2026-01-23T00:00:00Z", "open": 3.31, "high": 3.48, "low": 3.2, "close": 3.43, "volume": 201707300}, {"timestamp": "2026-01-26T00:00:00Z", "open": 3.45, "high": 3.62, "low": 3.35, "close": 3.53, "volume": 245423600}, {"timestamp": "2026-01-27T00:00:00Z", "open": 3.58, "high": 3.88, "low": 3.54, "close": 3.88, "volume": 239328100}, {"timestamp": "2026-01-28T00:00:00Z", "open": 4.15, "high": 4.26, "low": 4.13, "close": 4.26, "volume": 82785530}, {"timestamp": "2026-01-29T00:00:00Z", "open": 4.55, "high": 4.68, "low": 4.34, "close": 4.68, "volume": 624639100}, {"timestamp": "2026-01-30T00:00:00Z", "open": 4.49, "high": 4.5, "low": 4.22, "close": 4.22, "volume": 278270000}, {"timestamp": "2026-02-02T00:00:00Z", "open": 3.8, "high": 4.12, "low": 3.8, "close": 3.8, "volume": 592590300}, {"timestamp": "2026-02-03T00:00:00Z", "open": 3.95, "high": 4.18, "low": 3.91, "close": 4.18, "volume": 224397900}, {"timestamp": "2026-02-04T00:00:00Z", "open": 4.4, "high": 4.59, "low": 4.01, "close": 4.12, "volume": 603109700}, {"timestamp": "2026-02-05T00:00:00Z", "open": 3.95, "high": 4.15, "low": 3.85, "close": 3.92, "volume": 341750200}, {"timestamp": "2026-02-06T00:00:00Z", "open": 3.93, "high": 4.21, "low": 3.79, "close": 3.95, "volume": 353203500}, {"timestamp": "2026-02-09T00:00:00Z", "open": 4.07, "high": 4.25, "low": 4.03, "close": 4.06, "volume": 273101100}, {"timestamp": "2026-02-10T00:00:00Z", "open": 4.07, "high": 4.07, "low": 3.91, "close": 4.0, "volume": 170395900}, {"timestamp": "2026-02-11T00:00:00Z", "open": 4.01, "high": 4.4, "low": 3.98, "close": 4.4, "volume": 473112400}, {"timestamp": "2026-02-12T00:00:00Z", "open": 4.21, "high": 4.27, "low": 4.08, "close": 4.13, "volume": 345680000}, {"timestamp": "2026-02-13T00:00:00Z", "open": 4.05, "high": 4.11, "low": 3.98, "close": 4.0, "volume": 160116600}, {"timestamp": "2026-02-16T00:00:00Z", "open": 3.98, "high": 4.04, "low": 3.94, "close": 3.95, "volume": 130134500}, {"timestamp": "2026-02-17T00:00:00Z", "open": 3.95, "high": 3.97, "low": 3.85, "close": 3.85, "volume": 122058700}, {"timestamp": "2026-02-18T00:00:00Z", "open": 3.87, "high": 4.05, "low": 3.85, "close": 3.95, "volume": 207406400}, {"timestamp": "2026-02-19T00:00:00Z", "open": 3.95, "high": 4.04, "low": 3.63, "close": 3.68, "volume": 228733600}, {"timestamp": "2026-02-20T00:00:00Z", "open": 3.8, "high": 3.82, "low": 3.68, "close": 3.72, "volume": 74311770}, {"timestamp": "2026-02-23T00:00:00Z", "open": 3.77, "high": 3.95, "low": 3.76, "close": 3.79, "volume": 118722200}, {"timestamp": "2026-02-24T00:00:00Z", "open": 3.82, "high": 3.91, "low": 3.67, "close": 3.82, "volume": 183475800}, {"timestamp": "2026-02-25T00:00:00Z", "open": 3.91, "high": 4.08, "low": 3.72, "close": 3.95, "volume": 270057500}, {"timestamp": "2026-02-26T00:00:00Z", "open": 3.94, "high": 4.15, "low": 3.88, "close": 3.94, "volume": 239848100}, {"timestamp": "2026-02-27T00:00:00Z", "open": 3.95, "high": 4.02, "low": 3.59, "close": 3.59, "volume": 282100800}]