[{"timestamp": "2025-02-27T00:00:00Z", "open": 3.66, "high": 3.72, "low": 3.66, "close": 3.71, "volume": 51848858}, {"timestamp": "2025-02-28T00:00:00Z", "open": 3.69, "high": 3.77, "low": 3.68, "close": 3.77, "volume": 49873450}, {"timestamp": "2025-03-03T00:00:00Z", "open": 3.76, "high": 3.8, "low": 3.73, "close": 3.74, "volume": 59675870}, {"timestamp": "2025-03-04T00:00:00Z", "open": 3.73, "high": 3.74, "low": 3.66, "close": 3.67, "volume": 37587338}, {"timestamp": "2025-03-05T00:00:00Z", "open": 3.69, "high": 3.78, "low": 3.68, "close": 3.77, "volume": 51233794}, {"timestamp": "2025-03-06T00:00:00Z", "open": 3.79, "high": 3.92, "low": 3.79, "close": 3.91, "volume": 98032710}, {"timestamp": "2025-03-07T00:00:00Z", "open": 4.06, "high": 4.15, "low": 3.99, "close": 4.05, "volume": 175791984}, {"timestamp": "2025-03-10T00:00:00Z", "open": 4.05, "high": 4.08, "low": 4.0, "close": 4.01, "volume": 75117103}, {"timestamp": "2025-03-11T00:00:00Z", "open": 4.0, "high": 4.04, "low": 3.8, "close": 4.0, "volume": 80377361}, {"timestamp": "2025-03-12T00:00:00Z", "open": 3.92, "high": 3.93, "low": 3.86, "close": 3.9, "volume": 95917919}, {"timestamp": "2025-03-13T00:00:00Z", "open": 3.91, "high": 3.97, "low": 3.91, "close": 3.94, "volume": 66523190}, {"timestamp": "2025-03-14T00:00:00Z", "open": 3.95, "high": 4.03, "low": 3.95, "close": 4.01, "volume": 83566268}, {"timestamp": "2025-03-17T00:00:00Z", "open": 4.02, "high": 4.05, "low": 3.92, "close": 4.0, "volume": 84226840}, {"timestamp": "2025-03-18T00:00:00Z", "open": 3.97, "high": 4.0, "low": 3.94, "close": 3.94, "volume": 67166548}, {"timestamp": "2025-03-19T00:00:00Z", "open": 3.7, "high": 3.77, "low": 3.55, "close": 3.55, "volume": 95511828}, {"timestamp": "2025-03-20T00:00:00Z", "open": 3.55, "high": 3.65, "low": 3.46, "close": 3.54, "volume": 82458214}, {"timestamp": "2025-03-21T00:00:00Z", "open": 3.51, "high": 3.52, "low": 3.21, "close": 3.24, "volume": 72360870}, {"timestamp": "2025-03-24T00:00:00Z", "open": 3.23, "high": 3.34, "low": 3.13, "close": 3.28, "volume": 66762484}, {"timestamp": "2025-03-25T00:00:00Z", "open": 3.32, "high": 3.45, "low": 3.3, "close": 3.42, "volume": 54061080}, {"timestamp": "2025-03-26T00:00:00Z", "open": 3.37, "high": 3.46, "low": 3.37, "close": 3.43, "volume": 49371605}, {"timestamp": "2025-03-27T00:00:00Z", "open": 3.44, "high": 3.53, "low": 3.44, "close": 3.44, "volume": 52184608}, {"timestamp": "2025-03-28T00:00:00Z", "open": 3.44, "high": 3.54, "low": 3.39, "close": 3.51, "volume": 50784087}, {"timestamp": "2025-04-02T00:00:00Z", "open": 3.5, "high": 3.58, "low": 3.5, "close": 3.53, "volume": 44286753}, {"timestamp": "2025-04-03T00:00:00Z", "open": 3.52, "high": 3.58, "low": 3.5, "close": 3.51, "volume": 41847376}, {"timestamp": "2025-04-04T00:00:00Z", "open": 3.5, "high": 3.52, "low": 3.43, "close": 3.44, "volume": 43281402}, {"timestamp": "2025-04-07T00:00:00Z", "open": 3.39, "high": 3.56, "low": 3.34, "close": 3.5, "volume": 92817060}, {"timestamp": "2025-04-08T00:00:00Z", "open": 3.53, "high": 3.59, "low": 3.51, "close": 3.51, "volume": 64607283}, {"timestamp": "2025-04-09T00:00:00Z", "open": 3.5, "high": 3.52, "low": 3.43, "close": 3.43, "volume": 42112030}, {"timestamp": "2025-04-10T00:00:00Z", "open": 3.51, "high": 3.54, "low": 3.39, "close": 3.39, "volume": 57247806}, {"timestamp": "2025-04-11T00:00:00Z", "open": 3.41, "high": 3.49, "low": 3.39, "close": 3.45, "volume": 56048295}, {"timestamp": "2025-04-14T00:00:00Z", "open": 3.47, "high": 3.51, "low": 3.44, "close": 3.45, "volume": 54124235}, {"timestamp": "2025-04-15T00:00:00Z", "open": 3.45, "high": 3.49, "low": 3.43, "close": 3.44, "volume": 41048363}, {"timestamp": "2025-04-16T00:00:00Z", "open": 3.42, "high": 3.43, "low": 3.34, "close": 3.35, "volume": 32214206}, {"timestamp": "2025-04-17T00:00:00Z", "open": 3.34, "high": 3.39, "low": 3.31, "close": 3.37, "volume": 47482981}, {"timestamp": "2025-04-18T00:00:00Z", "open": 3.37, "high": 3.4, "low": 3.33, "close": 3.34, "volume": 26864534}, {"timestamp": "2025-04-21T00:00:00Z", "open": 3.36, "high": 3.37, "low": 3.29, "close": 3.3, "volume": 38579358}, {"timestamp": "2025-04-22T00:00:00Z", "open": 3.31, "high": 3.32, "low": 3.24, "close": 3.25, "volume": 28167559}, {"timestamp": "2025-04-24T00:00:00Z", "open": 3.26, "high": 3.44, "low": 3.25, "close": 3.35, "volume": 81986753}, {"timestamp": "2025-04-25T00:00:00Z", "open": 3.36, "high": 3.4, "low": 3.33, "close": 3.35, "volume": 38412316}, {"timestamp": "2025-04-28T00:00:00Z", "open": 3.36, "high": 3.38, "low": 3.29, "close": 3.3, "volume": 30493722}, {"timestamp": "2025-04-29T00:00:00Z", "open": 3.29, "high": 3.31, "low": 3.26, "close": 3.26, "volume": 26501720}, {"timestamp": "2025-04-30T00:00:00Z", "open": 3.26, "high": 3.28, "low": 3.19, "close": 3.2, "volume": 24608505}, {"timestamp": "2025-05-02T00:00:00Z", "open": 3.21, "high": 3.26, "low": 3.21, "close": 3.25, "volume": 30035332}, {"timestamp": "2025-05-05T00:00:00Z", "open": 3.27, "high": 3.33, "low": 3.25, "close": 3.28, "volume": 34054009}, {"timestamp": "2025-05-06T00:00:00Z", "open": 3.28, "high": 3.33, "low": 3.26, "close": 3.27, "volume": 43997052}, {"timestamp": "2025-05-07T00:00:00Z", "open": 3.27, "high": 3.28, "low": 3.2, "close": 3.2, "volume": 37107989}, {"timestamp": "2025-05-08T00:00:00Z", "open": 3.21, "high": 3.23, "low": 3.2, "close": 3.23, "volume": 13847272}, {"timestamp": "2025-05-09T00:00:00Z", "open": 3.26, "high": 3.29, "low": 3.23, "close": 3.25, "volume": 57258847}, {"timestamp": "2025-05-12T00:00:00Z", "open": 3.27, "high": 3.34, "low": 3.26, "close": 3.33, "volume": 82606268}, {"timestamp": "2025-05-13T00:00:00Z", "open": 3.33, "high": 3.4, "low": 3.3, "close": 3.36, "volume": 68849370}, {"timestamp": "2025-05-14T00:00:00Z", "open": 3.36, "high": 3.38, "low": 3.32, "close": 3.33, "volume": 51023395}, {"timestamp": "2025-05-15T00:00:00Z", "open": 3.33, "high": 3.35, "low": 3.27, "close": 3.29, "volume": 41791817}, {"timestamp": "2025-05-16T00:00:00Z", "open": 3.28, "high": 3.43, "low": 3.28, "close": 3.39, "volume": 89929753}, {"timestamp": "2025-05-20T00:00:00Z", "open": 3.39, "high": 3.48, "low": 3.35, "close": 3.36, "volume": 55377365}, {"timestamp": "2025-05-21T00:00:00Z", "open": 3.33, "high": 3.34, "low": 3.25, "close": 3.26, "volume": 47393209}, {"timestamp": "2025-05-22T00:00:00Z", "open": 3.26, "high": 3.29, "low": 3.24, "close": 3.25, "volume": 27965131}, {"timestamp": "2025-05-23T00:00:00Z", "open": 3.25, "high": 3.27, "low": 3.2, "close": 3.22, "volume": 24747737}, {"timestamp": "2025-05-26T00:00:00Z", "open": 3.23, "high": 3.24, "low": 3.15, "close": 3.17, "volume": 27994811}, {"timestamp": "2025-05-27T00:00:00Z", "open": 3.16, "high": 3.18, "low": 3.08, "close": 3.09, "volume": 32942617}, {"timestamp": "2025-05-28T00:00:00Z", "open": 3.08, "high": 3.09, "low": 3.01, "close": 3.03, "volume": 37653101}, {"timestamp": "2025-05-29T00:00:00Z", "open": 3.03, "high": 3.06, "low": 3.01, "close": 3.01, "volume": 19511482}, {"timestamp": "2025-05-30T00:00:00Z", "open": 3.0, "high": 3.01, "low": 2.95, "close": 2.99, "volume": 22171487}, {"timestamp": "2025-06-02T00:00:00Z", "open": 2.96, "high": 2.98, "low": 2.91, "close": 2.91, "volume": 26924525}, {"timestamp": "2025-06-03T00:00:00Z", "open": 2.94, "high": 2.98, "low": 2.93, "close": 2.97, "volume": 23359899}, {"timestamp": "2025-06-04T00:00:00Z", "open": 2.96, "high": 3.04, "low": 2.95, "close": 3.04, "volume": 34026622}, {"timestamp": "2025-06-05T00:00:00Z", "open": 3.03, "high": 3.04, "low": 3.0, "close": 3.03, "volume": 9233626}, {"timestamp": "2025-06-10T00:00:00Z", "open": 3.04, "high": 3.08, "low": 3.04, "close": 3.07, "volume": 26806927}, {"timestamp": "2025-06-11T00:00:00Z", "open": 3.07, "high": 3.11, "low": 3.05, "close": 3.07, "volume": 33984325}, {"timestamp": "2025-06-12T00:00:00Z", "open": 3.05, "high": 3.07, "low": 2.98, "close": 2.99, "volume": 27065527}, {"timestamp": "2025-06-13T00:00:00Z", "open": 2.87, "high": 2.98, "low": 2.81, "close": 2.95, "volume": 45711155}, {"timestamp": "2025-06-16T00:00:00Z", "open": 2.93, "high": 2.97, "low": 2.89, "close": 2.95, "volume": 24294051}, {"timestamp": "2025-06-17T00:00:00Z", "open": 2.94, "high": 2.97, "low": 2.9, "close": 2.9, "volume": 17942313}, {"timestamp": "2025-06-18T00:00:00Z", "open": 2.89, "high": 2.91, "low": 2.83, "close": 2.84, "volume": 23444803}, {"timestamp": "2025-06-19T00:00:00Z", "open": 2.86, "high": 2.89, "low": 2.81, "close": 2.82, "volume": 19240373}, {"timestamp": "2025-06-20T00:00:00Z", "open": 2.84, "high": 2.88, "low": 2.83, "close": 2.86, "volume": 31536541}, {"timestamp": "2025-06-23T00:00:00Z", "open": 2.85, "high": 2.85, "low": 2.8, "close": 2.82, "volume": 19988530}, {"timestamp": "2025-06-24T00:00:00Z", "open": 2.89, "high": 2.94, "low": 2.87, "close": 2.93, "volume": 34890932}, {"timestamp": "2025-06-25T00:00:00Z", "open": 2.93, "high": 2.95, "low": 2.9, "close": 2.91, "volume": 22712763}, {"timestamp": "2025-06-26T00:00:00Z", "open": 2.92, "high": 2.97, "low": 2.92, "close": 2.95, "volume": 30727793}, {"timestamp": "2025-06-27T00:00:00Z", "open": 2.96, "high": 2.97, "low": 2.9, "close": 2.95, "volume": 22725802}, {"timestamp": "2025-06-30T00:00:00Z", "open": 2.95, "high": 3.05, "low": 2.95, "close": 3.04, "volume": 50422199}, {"timestamp": "2025-07-01T00:00:00Z", "open": 3.04, "high": 3.12, "low": 3.02, "close": 3.09, "volume": 58040861}, {"timestamp": "2025-07-02T00:00:00Z", "open": 3.09, "high": 3.17, "low": 3.07, "close": 3.12, "volume": 53590051}, {"timestamp": "2025-07-03T00:00:00Z", "open": 3.14, "high": 3.19, "low": 3.14, "close": 3.15, "volume": 45095765}, {"timestamp": "2025-07-04T00:00:00Z", "open": 3.16, "high": 3.17, "low": 3.12, "close": 3.14, "volume": 26543663}, {"timestamp": "2025-07-07T00:00:00Z", "open": 3.1, "high": 3.1, "low": 3.05, "close": 3.05, "volume": 23437822}, {"timestamp": "2025-07-08T00:00:00Z", "open": 3.06, "high": 3.08, "low": 3.0, "close": 3.01, "volume": 23413009}, {"timestamp": "2025-07-09T00:00:00Z", "open": 3.01, "high": 3.07, "low": 3.01, "close": 3.07, "volume": 27517625}, {"timestamp": "2025-07-10T00:00:00Z", "open": 3.09, "high": 3.14, "low": 3.08, "close": 3.13, "volume": 37595545}, {"timestamp": "2025-07-11T00:00:00Z", "open": 3.14, "high": 3.16, "low": 3.09, "close": 3.14, "volume": 39954784}, {"timestamp": "2025-07-14T00:00:00Z", "open": 3.14, "high": 3.18, "low": 3.12, "close": 3.16, "volume": 50128050}, {"timestamp": "2025-07-16T00:00:00Z", "open": 3.16, "high": 3.36, "low": 3.1, "close": 3.17, "volume": 145107269}, {"timestamp": "2025-07-17T00:00:00Z", "open": 3.21, "high": 3.27, "low": 3.21, "close": 3.26, "volume": 48330658}, {"timestamp": "2025-07-18T00:00:00Z", "open": 3.26, "high": 3.26, "low": 3.2, "close": 3.23, "volume": 45278289}, {"timestamp": "2025-07-21T00:00:00Z", "open": 3.24, "high": 3.31, "low": 3.24, "close": 3.3, "volume": 50710633}, {"timestamp": "2025-07-22T00:00:00Z", "open": 3.3, "high": 3.39, "low": 3.27, "close": 3.34, "volume": 89226948}, {"timestamp": "2025-07-23T00:00:00Z", "open": 3.35, "high": 3.38, "low": 3.31, "close": 3.34, "volume": 52282412}, {"timestamp": "2025-07-24T00:00:00Z", "open": 3.34, "high": 3.38, "low": 3.33, "close": 3.36, "volume": 54730873}, {"timestamp": "2025-07-25T00:00:00Z", "open": 3.36, "high": 3.37, "low": 3.3, "close": 3.3, "volume": 39054862}, {"timestamp": "2025-07-28T00:00:00Z", "open": 3.31, "high": 3.37, "low": 3.31, "close": 3.33, "volume": 62059015}, {"timestamp": "2025-07-29T00:00:00Z", "open": 3.33, "high": 3.38, "low": 3.33, "close": 3.34, "volume": 50134854}, {"timestamp": "2025-07-30T00:00:00Z", "open": 3.35, "high": 3.44, "low": 3.32, "close": 3.35, "volume": 104151408}, {"timestamp": "2025-07-31T00:00:00Z", "open": 3.36, "high": 3.39, "low": 3.35, "close": 3.36, "volume": 60553316}, {"timestamp": "2025-08-01T00:00:00Z", "open": 3.36, "high": 3.38, "low": 3.33, "close": 3.35, "volume": 45166140}, {"timestamp": "2025-08-04T00:00:00Z", "open": 3.36, "high": 3.43, "low": 3.36, "close": 3.41, "volume": 77738423}, {"timestamp": "2025-08-05T00:00:00Z", "open": 3.42, "high": 3.47, "low": 3.41, "close": 3.41, "volume": 70811367}, {"timestamp": "2025-08-06T00:00:00Z", "open": 3.43, "high": 3.44, "low": 3.38, "close": 3.42, "volume": 61982725}, {"timestamp": "2025-08-07T00:00:00Z", "open": 3.43, "high": 3.47, "low": 3.43, "close": 3.45, "volume": 56856898}, {"timestamp": "2025-08-08T00:00:00Z", "open": 3.45, "high": 3.5, "low": 3.42, "close": 3.46, "volume": 67329786}, {"timestamp": "2025-08-11T00:00:00Z", "open": 3.48, "high": 3.56, "low": 3.48, "close": 3.56, "volume": 52055787}, {"timestamp": "2025-08-12T00:00:00Z", "open": 3.56, "high": 3.56, "low": 3.45, "close": 3.46, "volume": 61253017}, {"timestamp": "2025-08-13T00:00:00Z", "open": 3.39, "high": 3.4, "low": 3.33, "close": 3.33, "volume": 62690448}, {"timestamp": "2025-08-14T00:00:00Z", "open": 3.32, "high": 3.35, "low": 3.29, "close": 3.3, "volume": 43993554}, {"timestamp": "2025-08-15T00:00:00Z", "open": 3.3, "high": 3.63, "low": 3.28, "close": 3.55, "volume": 277066824}, {"timestamp": "2025-08-18T00:00:00Z", "open": 3.62, "high": 3.74, "low": 3.55, "close": 3.73, "volume": 158244836}, {"timestamp": "2025-08-19T00:00:00Z", "open": 3.73, "high": 3.84, "low": 3.63, "close": 3.66, "volume": 112063637}, {"timestamp": "2025-08-20T00:00:00Z", "open": 3.65, "high": 4.02, "low": 3.57, "close": 4.0, "volume": 298272782}, {"timestamp": "2025-08-21T00:00:00Z", "open": 4.02, "high": 4.32, "low": 3.97, "close": 4.23, "volume": 354381589}, {"timestamp": "2025-08-22T00:00:00Z", "open": 4.21, "high": 4.27, "low": 4.1, "close": 4.11, "volume": 162501358}, {"timestamp": "2025-08-25T00:00:00Z", "open": 4.14, "high": 4.25, "low": 4.06, "close": 4.16, "volume": 199297322}, {"timestamp": "2025-08-26T00:00:00Z", "open": 4.18, "high": 4.43, "low": 4.1, "close": 4.1, "volume": 360452390}, {"timestamp": "2025-08-27T00:00:00Z", "open": 4.15, "high": 4.16, "low": 3.89, "close": 3.91, "volume": 146681483}, {"timestamp": "2025-08-28T00:00:00Z", "open": 3.92, "high": 4.03, "low": 3.83, "close": 3.88, "volume": 199722400}, {"timestamp": "2025-08-29T00:00:00Z", "open": 3.86, "high": 3.93, "low": 3.77, "close": 3.8, "volume": 106097413}, {"timestamp": "2025-09-01T00:00:00Z", "open": 3.78, "high": 3.89, "low": 3.78, "close": 3.84, "volume": 80093487}, {"timestamp": "2025-09-02T00:00:00Z", "open": 3.85, "high": 3.93, "low": 3.58, "close": 3.72, "volume": 127572006}, {"timestamp": "2025-09-03T00:00:00Z", "open": 3.74, "high": 3.75, "low": 3.65, "close": 3.66, "volume": 93360582}, {"timestamp": "2025-09-04T00:00:00Z", "open": 3.69, "high": 3.9, "low": 3.69, "close": 3.82, "volume": 113975850}, {"timestamp": "2025-09-05T00:00:00Z", "open": 3.85, "high": 3.88, "low": 3.72, "close": 3.75, "volume": 66563182}, {"timestamp": "2025-09-08T00:00:00Z", "open": 3.7, "high": 3.7, "low": 3.51, "close": 3.53, "volume": 97508082}, {"timestamp": "2025-09-09T00:00:00Z", "open": 3.55, "high": 3.63, "low": 3.5, "close": 3.53, "volume": 63753619}, {"timestamp": "2025-09-10T00:00:00Z", "open": 3.58, "high": 3.72, "low": 3.57, "close": 3.58, "volume": 79429632}, {"timestamp": "2025-09-11T00:00:00Z", "open": 3.6, "high": 3.64, "low": 3.42, "close": 3.42, "volume": 77211873}, {"timestamp": "2025-09-12T00:00:00Z", "open": 3.42, "high": 3.47, "low": 3.34, "close": 3.41, "volume": 64622931}, {"timestamp": "2025-09-15T00:00:00Z", "open": 3.41, "high": 3.62, "low": 3.36, "close": 3.61, "volume": 94271787}, {"timestamp": "2025-09-16T00:00:00Z", "open": 3.62, "high": 3.76, "low": 3.61, "close": 3.74, "volume": 112896207}, {"timestamp": "2025-09-17T00:00:00Z", "open": 3.72, "high": 3.8, "low": 3.7, "close": 3.71, "volume": 66452085}, {"timestamp": "2025-09-18T00:00:00Z", "open": 3.74, "high": 3.79, "low": 3.63, "close": 3.64, "volume": 73468664}, {"timestamp": "2025-09-19T00:00:00Z", "open": 3.65, "high": 3.72, "low": 3.6, "close": 3.72, "volume": 78534997}, {"timestamp": "2025-09-22T00:00:00Z", "open": 3.78, "high": 3.8, "low": 3.73, "close": 3.74, "volume": 63678931}, {"timestamp": "2025-09-23T00:00:00Z", "open": 3.71, "high": 3.8, "low": 3.65, "close": 3.67, "volume": 88017054}, {"timestamp": "2025-09-24T00:00:00Z", "open": 3.67, "high": 3.69, "low": 3.59, "close": 3.66, "volume": 70660829}, {"timestamp": "2025-09-25T00:00:00Z", "open": 3.69, "high": 3.79, "low": 3.65, "close": 3.78, "volume": 117770429}, {"timestamp": "2025-09-26T00:00:00Z", "open": 3.8, "high": 3.83, "low": 3.7, "close": 3.71, "volume": 103304050}, {"timestamp": "2025-09-29T00:00:00Z", "open": 3.71, "high": 3.73, "low": 3.56, "close": 3.57, "volume": 66614721}, {"timestamp": "2025-09-30T00:00:00Z", "open": 3.58, "high": 3.61, "low": 3.53, "close": 3.56, "volume": 68041940}, {"timestamp": "2025-10-01T00:00:00Z", "open": 3.56, "high": 3.63, "low": 3.53, "close": 3.6, "volume": 85450072}, {"timestamp": "2025-10-02T00:00:00Z", "open": 3.6, "high": 3.65, "low": 3.5, "close": 3.51, "volume": 71346923}, {"timestamp": "2025-10-03T00:00:00Z", "open": 3.53, "high": 3.54, "low": 3.43, "close": 3.44, "volume": 53006922}, {"timestamp": "2025-10-06T00:00:00Z", "open": 3.46, "high": 3.48, "low": 3.4, "close": 3.4, "volume": 38907282}, {"timestamp": "2025-10-07T00:00:00Z", "open": 3.41, "high": 3.44, "low": 3.37, "close": 3.4, "volume": 56901085}, {"timestamp": "2025-10-08T00:00:00Z", "open": 3.4, "high": 3.43, "low": 3.34, "close": 3.35, "volume": 50651371}, {"timestamp": "2025-10-09T00:00:00Z", "open": 3.38, "high": 3.46, "low": 3.32, "close": 3.34, "volume": 51829116}, {"timestamp": "2025-10-10T00:00:00Z", "open": 3.35, "high": 3.37, "low": 3.3, "close": 3.32, "volume": 39374944}, {"timestamp": "2025-10-13T00:00:00Z", "open": 3.29, "high": 3.29, "low": 3.23, "close": 3.24, "volume": 45007501}, {"timestamp": "2025-10-14T00:00:00Z", "open": 3.26, "high": 3.27, "low": 3.15, "close": 3.15, "volume": 40577801}, {"timestamp": "2025-10-15T00:00:00Z", "open": 3.17, "high": 3.27, "low": 3.17, "close": 3.26, "volume": 44572501}, {"timestamp": "2025-10-16T00:00:00Z", "open": 3.27, "high": 3.51, "low": 3.25, "close": 3.51, "volume": 186934496}, {"timestamp": "2025-10-17T00:00:00Z", "open": 3.53, "high": 3.6, "low": 3.34, "close": 3.39, "volume": 177116222}, {"timestamp": "2025-10-20T00:00:00Z", "open": 3.4, "high": 3.41, "low": 3.32, "close": 3.32, "volume": 115409067}, {"timestamp": "2025-10-21T00:00:00Z", "open": 3.33, "high": 3.33, "low": 3.24, "close": 3.24, "volume": 56323515}, {"timestamp": "2025-10-22T00:00:00Z", "open": 3.25, "high": 3.35, "low": 3.22, "close": 3.27, "volume": 83760881}, {"timestamp": "2025-10-23T00:00:00Z", "open": 3.27, "high": 3.29, "low": 3.2, "close": 3.2, "volume": 52790403}, {"timestamp": "2025-10-24T00:00:00Z", "open": 3.22, "high": 3.32, "low": 3.21, "close": 3.27, "volume": 109431852}, {"timestamp": "2025-10-27T00:00:00Z", "open": 3.28, "high": 3.31, "low": 3.26, "close": 3.28, "volume": 65108416}, {"timestamp": "2025-10-28T00:00:00Z", "open": 3.28, "high": 3.29, "low": 3.26, "close": 3.26, "volume": 13544405}, {"timestamp": "2025-10-30T00:00:00Z", "open": 3.26, "high": 3.44, "low": 3.26, "close": 3.32, "volume": 136014000}, {"timestamp": "2025-10-31T00:00:00Z", "open": 3.33, "high": 3.36, "low": 3.31, "close": 3.35, "volume": 65636162}, {"timestamp": "2025-11-03T00:00:00Z", "open": 3.43, "high": 3.65, "low": 3.42, "close": 3.55, "volume": 144813489}, {"timestamp": "2025-11-04T00:00:00Z", "open": 3.54, "high": 3.7, "low": 3.52, "close": 3.61, "volume": 177811533}, {"timestamp": "2025-11-05T00:00:00Z", "open": 3.64, "high": 3.65, "low": 3.54, "close": 3.63, "volume": 124756950}, {"timestamp": "2025-11-06T00:00:00Z", "open": 3.64, "high": 3.65, "low": 3.55, "close": 3.56, "volume": 68602766}, {"timestamp": "2025-11-07T00:00:00Z", "open": 3.57, "high": 3.59, "low": 3.43, "close": 3.48, "volume": 68988499}, {"timestamp": "2025-11-10T00:00:00Z", "open": 3.48, "high": 3.56, "low": 3.46, "close": 3.46, "volume": 68307513}, {"timestamp": "2025-11-11T00:00:00Z", "open": 3.46, "high": 3.47, "low": 3.27, "close": 3.37, "volume": 85994158}, {"timestamp": "2025-11-12T00:00:00Z", "open": 3.38, "high": 3.4, "low": 3.29, "close": 3.31, "volume": 66942493}, {"timestamp": "2025-11-13T00:00:00Z", "open": 3.31, "high": 3.35, "low": 3.25, "close": 3.26, "volume": 60078157}, {"timestamp": "2025-11-14T00:00:00Z", "open": 3.26, "high": 3.28, "low": 3.19, "close": 3.22, "volume": 44790258}, {"timestamp": "2025-11-17T00:00:00Z", "open": 3.25, "high": 3.33, "low": 3.25, "close": 3.31, "volume": 56744008}, {"timestamp": "2025-11-18T00:00:00Z", "open": 3.29, "high": 3.31, "low": 3.22, "close": 3.26, "volume": 60333639}, {"timestamp": "2025-11-19T00:00:00Z", "open": 3.26, "high": 3.31, "low": 3.24, "close": 3.26, "volume": 66898227}, {"timestamp": "2025-11-20T00:00:00Z", "open": 3.28, "high": 3.38, "low": 3.27, "close": 3.32, "volume": 87416727}, {"timestamp": "2025-11-21T00:00:00Z", "open": 3.32, "high": 3.37, "low": 3.3, "close": 3.33, "volume": 59050254}, {"timestamp": "2025-11-24T00:00:00Z", "open": 3.34, "high": 3.54, "low": 3.34, "close": 3.46, "volume": 181808575}, {"timestamp": "2025-11-25T00:00:00Z", "open": 3.46, "high": 3.48, "low": 3.32, "close": 3.32, "volume": 104673786}, {"timestamp": "2025-11-26T00:00:00Z", "open": 3.34, "high": 3.35, "low": 3.28, "close": 3.28, "volume": 36273913}, {"timestamp": "2025-11-27T00:00:00Z", "open": 3.3, "high": 3.32, "low": 3.26, "close": 3.27, "volume": 46963636}, {"timestamp": "2025-11-28T00:00:00Z", "open": 3.28, "high": 3.3, "low": 3.23, "close": 3.24, "volume": 31825488}, {"timestamp": "2025-12-01T00:00:00Z", "open": 3.24, "high": 3.32, "low": 3.24, "close": 3.31, "volume": 40888030}, {"timestamp": "2025-12-02T00:00:00Z", "open": 3.31, "high": 3.33, "low": 3.24, "close": 3.25, "volume": 50712713}, {"timestamp": "2025-12-03T00:00:00Z", "open": 3.26, "high": 3.28, "low": 3.19, "close": 3.19, "volume": 61611731}, {"timestamp": "2025-12-04T00:00:00Z", "open": 3.2, "high": 3.24, "low": 3.15, "close": 3.15, "volume": 39258516}, {"timestamp": "2025-12-05T00:00:00Z", "open": 3.16, "high": 3.18, "low": 3.14, "close": 3.17, "volume": 33966272}, {"timestamp": "2025-12-08T00:00:00Z", "open": 3.19, "high": 3.26, "low": 3.19, "close": 3.22, "volume": 53733555}, {"timestamp": "2025-12-09T00:00:00Z", "open": 3.23, "high": 3.24, "low": 3.18, "close": 3.2, "volume": 43281081}, {"timestamp": "2025-12-10T00:00:00Z", "open": 3.21, "high": 3.23, "low": 3.17, "close": 3.17, "volume": 45484462}, {"timestamp": "2025-12-11T00:00:00Z", "open": 3.18, "high": 3.21, "low": 3.15, "close": 3.17, "volume": 68967008}, {"timestamp": "2025-12-12T00:00:00Z", "open": 3.18, "high": 3.21, "low": 3.16, "close": 3.18, "volume": 47841202}, {"timestamp": "2025-12-15T00:00:00Z", "open": 3.19, "high": 3.21, "low": 3.16, "close": 3.17, "volume": 47401281}, {"timestamp": "2025-12-16T00:00:00Z", "open": 3.17, "high": 3.18, "low": 3.08, "close": 3.09, "volume": 52376098}, {"timestamp": "2025-12-17T00:00:00Z", "open": 3.09, "high": 3.12, "low": 3.07, "close": 3.08, "volume": 25812505}, {"timestamp": "2025-12-18T00:00:00Z", "open": 3.09, "high": 3.1, "low": 3.07, "close": 3.08, "volume": 20612329}, {"timestamp": "2025-12-19T00:00:00Z", "open": 3.08, "high": 3.14, "low": 3.05, "close": 3.14, "volume": 50062526}, {"timestamp": "2025-12-22T00:00:00Z", "open": 3.16, "high": 3.16, "low": 3.05, "close": 3.05, "volume": 30836472}, {"timestamp": "2025-12-23T00:00:00Z", "open": 3.05, "high": 3.06, "low": 3.02, "close": 3.04, "volume": 29948982}, {"timestamp": "2025-12-24T00:00:00Z", "open": 3.04, "high": 3.06, "low": 3.02, "close": 3.04, "volume": 25508820}, {"timestamp": "2025-12-25T00:00:00Z", "open": 3.05, "high": 3.08, "low": 3.05, "close": 3.05, "volume": 14349124}, {"timestamp": "2025-12-26T00:00:00Z", "open": 3.05, "high": 3.06, "low": 3.02, "close": 3.05, "volume": 29927970}, {"timestamp": "2025-12-29T00:00:00Z", "open": 3.06, "high": 3.07, "low": 3.01, "close": 3.02, "volume": 29327772}, {"timestamp": "2025-12-30T00:00:00Z", "open": 3.03, "high": 3.14, "low": 3.01, "close": 3.07, "volume": 54101555}, {"timestamp": "2025-12-31T00:00:00Z", "open": 3.07, "high": 3.1, "low": 3.06, "close": 3.07, "volume": 37284488}, {"timestamp": "2026-01-02T00:00:00Z", "open": 3.08, "high": 3.13, "low": 3.08, "close": 3.13, "volume": 37320710}, {"timestamp": "2026-01-05T00:00:00Z", "open": 3.13, "high": 3.14, "low": 3.07, "close": 3.09, "volume": 53223740}, {"timestamp": "2026-01-06T00:00:00Z", "open": 3.1, "high": 3.14, "low": 3.09, "close": 3.12, "volume": 60600674}, {"timestamp": "2026-01-07T00:00:00Z", "open": 3.13, "high": 3.15, "low": 3.06, "close": 3.07, "volume": 37040818}, {"timestamp": "2026-01-08T00:00:00Z", "open": 3.07, "high": 3.11, "low": 3.02, "close": 3.1, "volume": 51095416}, {"timestamp": "2026-01-09T00:00:00Z", "open": 3.1, "high": 3.11, "low": 3.04, "close": 3.06, "volume": 29447163}, {"timestamp": "2026-01-12T00:00:00Z", "open": 3.06, "high": 3.09, "low": 3.05, "close": 3.06, "volume": 46586134}, {"timestamp": "2026-01-13T00:00:00Z", "open": 3.06, "high": 3.11, "low": 3.05, "close": 3.07, "volume": 94550389}, {"timestamp": "2026-01-14T00:00:00Z", "open": 3.07, "high": 3.09, "low": 3.03, "close": 3.03, "volume": 66822211}, {"timestamp": "2026-01-15T00:00:00Z", "open": 3.03, "high": 3.1, "low": 3.02, "close": 3.09, "volume": 64808720}, {"timestamp": "2026-01-16T00:00:00Z", "open": 3.1, "high": 3.12, "low": 3.06, "close": 3.12, "volume": 79800580}, {"timestamp": "2026-01-19T00:00:00Z", "open": 3.12, "high": 3.15, "low": 3.09, "close": 3.11, "volume": 66433651}, {"timestamp": "2026-01-20T00:00:00Z", "open": 3.1, "high": 3.11, "low": 3.06, "close": 3.08, "volume": 47621882}, {"timestamp": "2026-01-21T00:00:00Z", "open": 3.08, "high": 3.09, "low": 3.04, "close": 3.05, "volume": 38705522}, {"timestamp": "2026-01-22T00:00:00Z", "open": 3.06, "high": 3.1, "low": 3.06, "close": 3.09, "volume": 53162537}, {"timestamp": "2026-01-23T00:00:00Z", "open": 3.1, "high": 3.15, "low": 3.09, "close": 3.15, "volume": 87060340}, {"timestamp": "2026-01-26T00:00:00Z", "open": 3.13, "high": 3.26, "low": 3.12, "close": 3.22, "volume": 130957000}, {"timestamp": "2026-01-27T00:00:00Z", "open": 3.23, "high": 3.24, "low": 3.16, "close": 3.16, "volume": 93869780}, {"timestamp": "2026-01-28T00:00:00Z", "open": 3.16, "high": 3.24, "low": 3.16, "close": 3.21, "volume": 88292707}, {"timestamp": "2026-01-29T00:00:00Z", "open": 3.23, "high": 3.31, "low": 3.22, "close": 3.27, "volume": 125636437}, {"timestamp": "2026-01-30T00:00:00Z", "open": 3.29, "high": 3.3, "low": 3.22, "close": 3.3, "volume": 97110424}, {"timestamp": "2026-02-02T00:00:00Z", "open": 3.28, "high": 3.31, "low": 3.17, "close": 3.26, "volume": 93649658}, {"timestamp": "2026-02-03T00:00:00Z", "open": 3.3, "high": 3.39, "low": 3.28, "close": 3.38, "volume": 131495381}, {"timestamp": "2026-02-04T00:00:00Z", "open": 3.39, "high": 3.65, "low": 3.38, "close": 3.52, "volume": 291441636}, {"timestamp": "2026-02-05T00:00:00Z", "open": 3.53, "high": 3.61, "low": 3.43, "close": 3.44, "volume": 117965032}, {"timestamp": "2026-02-06T00:00:00Z", "open": 3.44, "high": 3.45, "low": 3.37, "close": 3.42, "volume": 81671968}, {"timestamp": "2026-02-09T00:00:00Z", "open": 3.45, "high": 3.56, "low": 3.45, "close": 3.55, "volume": 83637916}, {"timestamp": "2026-02-10T00:00:00Z", "open": 3.55, "high": 3.59, "low": 3.49, "close": 3.54, "volume": 127441311}, {"timestamp": "2026-02-11T00:00:00Z", "open": 3.51, "high": 3.53, "low": 3.46, "close": 3.47, "volume": 66356222}, {"timestamp": "2026-02-12T00:00:00Z", "open": 3.48, "high": 3.6, "low": 3.47, "close": 3.58, "volume": 67011926}, {"timestamp": "2026-02-13T00:00:00Z", "open": 3.6, "high": 3.65, "low": 3.53, "close": 3.65, "volume": 78589922}, {"timestamp": "2026-02-16T00:00:00Z", "open": 3.67, "high": 3.71, "low": 3.63, "close": 3.68, "volume": 80702505}, {"timestamp": "2026-02-17T00:00:00Z", "open": 3.69, "high": 3.78, "low": 3.59, "close": 3.69, "volume": 117346071}, {"timestamp": "2026-02-18T00:00:00Z", "open": 3.69, "high": 3.75, "low": 3.56, "close": 3.58, "volume": 79525411}, {"timestamp": "2026-02-19T00:00:00Z", "open": 3.6, "high": 3.6, "low": 3.42, "close": 3.44, "volume": 50800825}, {"timestamp": "2026-02-20T00:00:00Z", "open": 3.44, "high": 3.49, "low": 3.39, "close": 3.46, "volume": 43136224}, {"timestamp": "2026-02-23T00:00:00Z", "open": 3.49, "high": 3.52, "low": 3.44, "close": 3.45, "volume": 33815554}, {"timestamp": "2026-02-24T00:00:00Z", "open": 3.44, "high": 3.45, "low": 3.38, "close": 3.41, "volume": 28175268}, {"timestamp": "2026-02-25T00:00:00Z", "open": 3.4, "high": 3.71, "low": 3.31, "close": 3.51, "volume": 136778760}, {"timestamp": "2026-02-26T00:00:00Z", "open": 3.52, "high": 3.65, "low": 3.45, "close": 3.54, "volume": 113127202}, {"timestamp": "2026-02-27T00:00:00Z", "open": 3.55, "high": 3.56, "low": 3.35, "close": 3.37, "volume": 81699850}]